[{"s": "intel-r-core-tm-i3-cpu-m-380", "t": "Процессор Intel Core i3-380M: Обзор характеристик и возможностей", "i": "🖥️", "c": "kompyutery-i-noutbuki"}, {"s": "internet-dlya-doma-cherez-sim-kartu", "t": "Интернет для дома через сим карту: выбор тарифа, роутера и настройка", "i": "📶", "c": "set-i-internet"}, {"s": "interfejs-ethernet-rj-45", "t": "Интерфейс Ethernet RJ45: Устройство, стандарты и настройка подключения", "i": "📶", "c": "set-i-internet"}, {"s": "internet-na-dache-varianty", "t": "Интернет на даче: варианты подключения и выбор оборудования", "i": "📶", "c": "set-i-internet"}, {"s": "interesnye-ustrojstva-dlya-umnogo-doma", "t": "Интересные устройства для умного дома: ТОП-10 гаджетов 2026", "i": "🏠", "c": "umnyj-dom"}, {"s": "internet-most-dlya-chastnogo-doma", "t": "Интернет-мост для частного дома: выбор, настройка и подключение", "i": "📶", "c": "set-i-internet"}, {"s": "infinix-smart-9-otzyvy", "t": "Infinix Smart 9: честные отзывы, плюсы и минусы смартфона", "i": "📱", "c": "smartfony-i-planshety"}, {"s": "interesnyj-shrift-dlya-nika", "t": "Интересный шрифт для ника: как выделиться в сети", "i": "💿", "c": "soft-i-prilozheniya"}, {"s": "internet-rabotaet-no-brauzery-ne-otkryvayut-stranitsy", "t": "Интернет есть, но браузер не открывает страницы: причины и решение", "i": "📶", "c": "set-i-internet"}, {"s": "intel-core-i7-740qm", "t": "Intel Core i7-740QM: характеристики, тесты и актуальность", "i": "🖥️", "c": "kompyutery-i-noutbuki"}, {"s": "interesnye-komandy-dlya-alisy-stantsii", "t": "Лучшие команды для Алисы на Яндекс Станции: полный список и инструкции", "i": "🏠", "c": "umnyj-dom"}, {"s": "internal-flight-estas-tonne", "t": "Внутренние рейсы и ESTA: правила для перелетов по Тонне и США", "i": "📶", "c": "set-i-internet"}, {"s": "internet-bez-routera-v-kvartire", "t": "Интернет без роутера в квартире: способы, плюсы и минусы", "i": "📶", "c": "set-i-internet"}, {"s": "instruktazh-voditelej-po-bezopasnosti-dorozhnogo-dvizheniya", "t": "Инструктаж водителей: правила, периодичность и безопасность", "i": "🚗", "c": "avtomobilnaya-elektronika"}, {"s": "intel-celeron-b815-apgrejd", "t": "Intel Celeron B815: Апгрейд и замена процессора", "i": "🖥️", "c": "kompyutery-i-noutbuki"}, {"s": "internet-v-chastnyj-dom-megafon", "t": "Интернет в частный дом МегаФон: подключение 4G и 5G", "i": "📶", "c": "set-i-internet"}, {"s": "instrumentalnaya-muzyka-skachat-flac", "t": "Инструментальная музыка скачать FLAC: гид по качеству звука и форматам", "i": "🎧", "c": "audio-i-video"}, {"s": "infinix-brend-kto-proizvoditel", "t": "Infinix: кто производитель, страна бренда и история компании", "i": "📱", "c": "smartfony-i-planshety"}, {"s": "interface-supports-all-obd2-protocols-programma", "t": "Interface Supports All OBD2 Protocols: Программа и настройка", "i": "🚗", "c": "avtomobilnaya-elektronika"}, {"s": "insert-knopka-na-klaviature", "t": "Клавиша Insert на клавиатуре: функции, назначение и переключение режимов", "i": "🖥️", "c": "kompyutery-i-noutbuki"}, {"s": "instruktsii-po-bezopasnosti-dorozhnogo-dvizheniya-dlya-voditelej", "t": "Безопасность вождения: Полное руководство для водителей", "i": "🚗", "c": "avtomobilnaya-elektronika"}, {"s": "integratsiya-mi-home-v-home-assistant", "t": "Интеграция Mi Home в Home Assistant: полное руководство", "i": "🏠", "c": "umnyj-dom"}, {"s": "instruktsiya-po-podache-deklaratsii-3-ndfl-cherez-lichnyj-kabinet-nalogoplatelshchika-dlya-fizicheskikh-lits", "t": "Как подать 3-НДФЛ через Личный кабинет: Пошаговая инструкция 2026", "i": "🔒", "c": "bezopasnost-i-akkaunty"}, {"s": "interfejs-zigbee-chto-eto", "t": "Интерфейс Zigbee: что это и как работает в умном доме", "i": "🏠", "c": "umnyj-dom"}, {"s": "internet-na-kompyutere-est-a-brauzer-ne-zagruzhaet-stranitsy", "t": "Интернет есть, а браузер не грузит: 7 рабочих способов починить", "i": "💿", "c": "soft-i-prilozheniya"}, {"s": "informatsiya-o-cheloveke-po-nomeru-pasporta", "t": "Поиск информации по номеру паспорта: мифы, риски и законные методы", "i": "🔒", "c": "bezopasnost-i-akkaunty"}, {"s": "interesnye-fakty-o-makdonaldse", "t": "Интересные факты о McDonald's: история, секреты и статистика", "i": "🏠", "c": "umnyj-dom"}, {"s": "intel-hm77-podderzhivaemye-protsessory", "t": "Intel HM77 поддерживаемые процессоры: полный список и совместимость", "i": "🖥️", "c": "kompyutery-i-noutbuki"}, {"s": "internet-filtry-keenetic-kakoj-vybrat", "t": "Интернет-фильтры Keenetic: какой выбрать и настроить?", "i": "📶", "c": "set-i-internet"}, {"s": "infrakrasnyj-filtr-dlya-obektiva", "t": "Инфракрасный фильтр для объектива: выбор и применение", "i": "🎧", "c": "audio-i-video"}, {"s": "instruktsiya-po-ustanovke-zashchitnogo-stekla-na-smartfon", "t": "Как наклеить защитное стекло на смартфон: пошаговая инструкция", "i": "📱", "c": "smartfony-i-planshety"}, {"s": "instruktor-sidit-v-telefone", "t": "Инструктор сидит в телефоне: причины, риски и что делать", "i": "🚗", "c": "avtomobilnaya-elektronika"}, {"s": "inskam-endoskop-prilozhenie-dlya-android-skachat", "t": "Inskam эндоскоп приложение для Android: скачать, настройка и обзор", "i": "💿", "c": "soft-i-prilozheniya"}, {"s": "internet-simka-dlya-modema-bezlimitnyj-tarify", "t": "Интернет симка для модема: лучшие безлимитные тарифы 2026", "i": "📶", "c": "set-i-internet"}, {"s": "interval-i-kadrov-v-kamere-chto-eto", "t": "Интервал I-кадров в камере: что это такое и как влияет на запись", "i": "⌚", "c": "elektronika-i-gadzhety"}, {"s": "intel-flash-image-tool", "t": "Intel Flash Image Tool: инструкция по сборке и прошивке BIOS", "i": "🔧", "c": "remont-i-diagnostika"}, {"s": "interesnye-funktsii-ajfona-11", "t": "Интересные функции айфона 11: скрытые возможности и трюки", "i": "📱", "c": "smartfony-i-planshety"}, {"s": "internet-dlya-pk-bezlimit", "t": "Безлимитный интернет для ПК и ноутбука: выбор и настройка", "i": "📶", "c": "set-i-internet"}, {"s": "insert-na-klaviature-gde", "t": "Где находится кнопка Insert на клавиатуре: поиск и функции", "i": "🖥️", "c": "kompyutery-i-noutbuki"}, {"s": "internet-dlya-avtomagnitoly-na-android", "t": "Как подключить интернет к Android-автомагнитоле: полное руководство", "i": "🚗", "c": "avtomobilnaya-elektronika"}, {"s": "intervalnaya-semka-chto-eto", "t": "Интервальная съемка: что это, как работает и зачем нужна", "i": "🎧", "c": "audio-i-video"}, {"s": "interesnye-korpusa-dlya-pk", "t": "Необычные и интересные корпуса для ПК: топ моделей и тренды", "i": "🖥️", "c": "kompyutery-i-noutbuki"}, {"s": "indikator-zhestkogo-diska-gorit-postoyanno", "t": "Почему индикатор жесткого диска горит постоянно: Диагностика и ремонт", "i": "🔧", "c": "remont-i-diagnostika"}, {"s": "interesnye-simvoly-dlya-teksta", "t": "Специальные символы для текста: красивые эмодзи и знаки 2026", "i": "💿", "c": "soft-i-prilozheniya"}, {"s": "interesnye-fakty-ob-igrakh", "t": "Интересные факты об играх: 15 удивительных историй из индустрии", "i": "🎮", "c": "igry-i-razvlecheniya"}, {"s": "interesnye-komandy-dlya-alisy", "t": "Топ лучших команд для Алисы: Умный дом, игры и полезные навыки", "i": "🏠", "c": "umnyj-dom"}, {"s": "internet-dlya-derevni-gde-net-svyazi", "t": "Интернет в деревне без связи: лучшие способы подключения 2026", "i": "📶", "c": "set-i-internet"}, {"s": "internet-kabel-skolko-zhil-dolzhno-byt", "t": "Интернет кабель: сколько жил нужно и как выбрать", "i": "📶", "c": "set-i-internet"}, {"s": "instruktsiya-po-zavyazyvaniyu-galstuka", "t": "Как завязать галстук: 7 лучших узлов для любого случая (Инструкция)", "i": "📁", "c": "drugoe"}, {"s": "intel-core-i5-2450m-apgrejd", "t": "Intel Core i5-2450M апгрейд: выбор процессора и видеокарты", "i": "🖥️", "c": "kompyutery-i-noutbuki"}, {"s": "internet-bez-simki-na-telefon", "t": "Как получить интернет на телефоне без сим-карты: полные способы", "i": "📱", "c": "smartfony-i-planshety"}, {"s": "internet-tsentr-yota-2-proshivka", "t": "Прошивка Yota 2: Обновление, разблокировка и настройка", "i": "📶", "c": "set-i-internet"}, {"s": "internet-est-no-stranitsy-ne-zagruzhayutsya-na-kompyutere", "t": "Интернет есть, но страницы не грузятся: решение на ПК", "i": "📶", "c": "set-i-internet"}, {"s": "internet-24-ggts-i-5-ggts-v-chem-raznitsa", "t": "Wi-Fi 2.4 ГГц и 5 ГГц: Полная разница, скорости и как выбрать", "i": "📶", "c": "set-i-internet"}, {"s": "internet-radio-dlya-android-skachat", "t": "Как скачать и установить интернет-радио на Android: Топ приложений и настройки", "i": "📱", "c": "smartfony-i-planshety"}, {"s": "insert-na-klaviature-dlya-chego", "t": "Клавиша Insert на клавиатуре: зачем нужна и как отключить", "i": "🖥️", "c": "kompyutery-i-noutbuki"}, {"s": "interfejs-rj-45-chto-eto", "t": "Интерфейс RJ 45: что это такое, виды и особенности подключения", "i": "📶", "c": "set-i-internet"}, {"s": "internet-est-a-prilozheniya-ne-rabotayut", "t": "Интернет есть, а приложения не работают: причины и решения", "i": "📶", "c": "set-i-internet"}, {"s": "installyatsionnyj-platezh-chto-eto-rostelekom", "t": "Инсталляционный платеж Ростелеком: что это и как оплатить", "i": "📶", "c": "set-i-internet"}, {"s": "interesnye-simvoly-dlya-nika", "t": "Топ интересных символов для ника: красивые значки и генераторы", "i": "🎮", "c": "igry-i-razvlecheniya"}, {"s": "internet-gde-net-svyazi", "t": "Как получить интернет без связи: спутниковые и автономные решения", "i": "📶", "c": "set-i-internet"}, {"s": "internet-na-dachu-varianty", "t": "Интернет на дачу: лучшие варианты подключения и выбор оборудования", "i": "📶", "c": "set-i-internet"}, {"s": "internet-wifi-kommutator-chto-eto", "t": "Интернет WiFi коммутатор: что это и как работает сеть", "i": "📶", "c": "set-i-internet"}, {"s": "informatsiya-o-cheloveke-po-fio-i-date-rozhdeniya-besplatno", "t": "Проверка информации по ФИО и дате рождения: бесплатные методы", "i": "🔒", "c": "bezopasnost-i-akkaunty"}, {"s": "insert-your-sim-card", "t": "Insert Your SIM Card: решение ошибки и настройка сети", "i": "📱", "c": "smartfony-i-planshety"}, {"s": "intruder-na-materinskoj-plate", "t": "Intruder на материнской плате: Причины и устранение", "i": "🖥️", "c": "kompyutery-i-noutbuki"}, {"s": "infinix-chto-za-firma", "t": "Infinix что за фирма: обзор бренда, модели и характеристики", "i": "📱", "c": "smartfony-i-planshety"}, {"s": "intel-gl40-podderzhivaemye-protsessory", "t": "Процессоры для Intel GL40: полные списки и совместимость", "i": "🖥️", "c": "kompyutery-i-noutbuki"}, {"s": "internet-dlya-kompyutera-cherez-sim-kartu", "t": "Интернет для компьютера через сим-карту: выбор модема и тарифа", "i": "📶", "c": "set-i-internet"}, {"s": "internet-radio-na-esp8266", "t": "Интернет радио на ESP8266: сборка и настройка своими руками", "i": "⌚", "c": "elektronika-i-gadzhety"}, {"s": "internet-cherez-220-volt-ustrojstvo", "t": "Интернет через 220 вольт: устройство Powerline и его настройка", "i": "📶", "c": "set-i-internet"}, {"s": "internet-rabotaet-no-nichego-ne-gruzit", "t": "Интернет работает, но ничего не грузит: причины и решение", "i": "📶", "c": "set-i-internet"}, {"s": "invertor-svarochnyj-mig-200-real-smart-n2a5", "t": "Обзор сварочного инвертора Mig 200 Real Smart N2A5: характеристики", "i": "🔧", "c": "remont-i-diagnostika"}, {"s": "insert-na-klaviature-noutbuka-gde", "t": "Где находится клавиша Insert на ноутбуке: расположение и замена", "i": "🖥️", "c": "kompyutery-i-noutbuki"}, {"s": "internet-est-no-ne-rabotaet-na-kompyutere-brauzer", "t": "Интернет есть, но браузер не работает: полное руководство по диагностике и ремонту", "i": "🖥️", "c": "kompyutery-i-noutbuki"}, {"s": "informatsiya-pro-rodinu-mat", "t": "Мемориальный комплекс «Родина-мать зовёт!» — история, архитектура и факты", "i": "📁", "c": "drugoe"}, {"s": "internet-usilitel-dlya-dachi-s-routerom", "t": "Интернет усилитель для дачи с роутером: выбор и настройка", "i": "📶", "c": "set-i-internet"}, {"s": "infrakrasnyj-tsvet-kak-vyglyadit", "t": "Инфракрасный цвет: как выглядит и где применяется", "i": "⌚", "c": "elektronika-i-gadzhety"}, {"s": "infrakrasnyj-teplovizor-dlya-telefona", "t": "Инфракрасный тепловизор для телефона: выбор, обзор и способы применения", "i": "⌚", "c": "elektronika-i-gadzhety"}, {"s": "inspektor-gims-kto-eto", "t": "Инспектор ГИБДД: кто это, права и обязанности сотрудника", "i": "🚗", "c": "avtomobilnaya-elektronika"}, {"s": "instruktazhi-po-bdd-s-voditelskim-sostavom-kakie-byvayut", "t": "Виды инструктажей по БДД с водителями: полный разбор", "i": "🚗", "c": "avtomobilnaya-elektronika"}, {"s": "intel-core-i5-3210m-apgrejd", "t": "Апгрейд ноутбука с Intel Core i5-3210M: стоит ли менять процессор и что лучше?", "i": "🖥️", "c": "kompyutery-i-noutbuki"}, {"s": "infrakrasnaya-kamera-dlya-telefona", "t": "Инфракрасная камера для телефона: выбор, обзор и настройка", "i": "🔧", "c": "remont-i-diagnostika"}, {"s": "internet-cherez-antennu-v-chastnom-dome", "t": "Интернет через антенну в частном доме: выбор оборудования и настройка", "i": "📶", "c": "set-i-internet"}, {"s": "internet-tsentr-jota-2", "t": "Интернет-центр Yota 2: обзор, настройка и тарифы", "i": "📶", "c": "set-i-internet"}, {"s": "intellekt-park-skachat-prilozhenie", "t": "Приложение Интеллект Парк: как скачать и установить на смартфон", "i": "💿", "c": "soft-i-prilozheniya"}, {"s": "intel-core-i3-370m-apgrejd", "t": "Intel Core i3 370M апгрейд: выбор SSD, RAM и возможности", "i": "🖥️", "c": "kompyutery-i-noutbuki"}, {"s": "internet-cherez-modem-na-dache", "t": "Интернет через модем на даче: выбор оператора, оборудования и настройка", "i": "📶", "c": "set-i-internet"}, {"s": "insert-net-na-klaviature", "t": "Не хватает клавиши Insert: как найти, включить и настроить функционал", "i": "🖥️", "c": "kompyutery-i-noutbuki"}, {"s": "inskam-ne-rabotaet-kamera-endoskop", "t": "Inskam не работает камера: причины и ремонт эндоскопа", "i": "🔧", "c": "remont-i-diagnostika"}, {"s": "interesnye-znaki-i-simvoly", "t": "Интересные знаки и символы: Справочник спецсимволов для текста и кода", "i": "💿", "c": "soft-i-prilozheniya"}, {"s": "internet-po-sim-karte-dlya-routera", "t": "Интернет по СИМ-карте для роутера: выбор и настройка", "i": "📶", "c": "set-i-internet"}, {"s": "internet-svistok-dlya-kompyutera", "t": "Интернет-свисток для компьютера: выбор, настройка и скорость", "i": "📶", "c": "set-i-internet"}, {"s": "intrusion-win-ms17-010", "t": "Уязвимость MS17-010: полная защита от EternalBlue", "i": "🔒", "c": "bezopasnost-i-akkaunty"}, {"s": "instruktazh-voditelej-pered-vyezdom-na-liniyu-obrazets", "t": "Инструктаж водителей перед выездом: образец, правила, журнал", "i": "🚗", "c": "avtomobilnaya-elektronika"}, {"s": "internet-tsentr-yota-2-instruktsiya", "t": "Интернет Центр Yota 2: Полная инструкция по настройке", "i": "📶", "c": "set-i-internet"}, {"s": "instruktsiya-marshall-major-4", "t": "Полная инструкция Marshall Major IV: подключение, зарядка и кнопки", "i": "🎧", "c": "audio-i-video"}, {"s": "internet-v-chastnyj-dom-svoimi-rukami", "t": "Как провести интернет в частный дом своими руками: Полное руководство 2026", "i": "📶", "c": "set-i-internet"}, {"s": "interesnye-veshchi-na-3d-printere", "t": "Что печатать на 3D принтере: идеи для дома, творчества и заработка", "i": "🖨️", "c": "3d-pechat-i-modelirovanie"}, {"s": "informatsiya-s-zakrytoj-stranitsy-vk", "t": "Как получить доступ к информации с закрытой страницы ВК", "i": "🔒", "c": "bezopasnost-i-akkaunty"}, {"s": "internet-rozetka-rj45-kak-podklyuchit", "t": "Как подключить интернет розетку RJ45: схема, порядок действий и ошибки", "i": "📶", "c": "set-i-internet"}, {"s": "inf-storonnego-proizvoditelya-ne-soderzhit-informatsii-o-podpisi-win-10", "t": "Ошибка INF: информация о подписи Win 10 отсутствует — полное руководство", "i": "💿", "c": "soft-i-prilozheniya"}, {"s": "inbox-e70-parol-po-umolchaniyu", "t": "Inbox E70 пароль по умолчанию: сброс и настройка", "i": "📶", "c": "set-i-internet"}, {"s": "initsializatsiya-ssd-m2-diska-v-windows-10", "t": "Инициализация SSD M.2 в Windows 10: Полная инструкция", "i": "🖥️", "c": "kompyutery-i-noutbuki"}, {"s": "interesnye-kombinatsii-klavish-na-klaviature", "t": "Топ-20 горячих клавиш для скорости работы на Windows и Mac", "i": "🖥️", "c": "kompyutery-i-noutbuki"}, {"s": "internet-cherez-antennyj-kabel", "t": "Интернет через антенный кабель: как подключить ТВ и раздать сеть", "i": "📶", "c": "set-i-internet"}, {"s": "informatsiya-o-cheloveke-po-nomeru-karty", "t": "Как узнать владельца по номеру карты: мифы, реальность и защита", "i": "🔒", "c": "bezopasnost-i-akkaunty"}, {"s": "internet-v-avtomobil-dlya-golovnogo-ustrojstva", "t": "Как подключить интернет в автомобиль к головному устройству: гайд 2026", "i": "🚗", "c": "avtomobilnaya-elektronika"}, {"s": "internet-provoda-v-okeane", "t": "Интернет провода в океане: устройство подводных кабелей", "i": "📶", "c": "set-i-internet"}, {"s": "internet-tinkoff-dlya-modema", "t": "Интернет Тинькофф для модема: настройка, тарифы и активация сим-карты", "i": "📶", "c": "set-i-internet"}, {"s": "interesnye-podelki-na-3d-printere", "t": "Интересные поделки на 3D принтере: идеи и инструкции", "i": "🖨️", "c": "3d-pechat-i-modelirovanie"}, {"s": "interesnye-fakty-o-kompyuternykh-igrakh", "t": "Интересные факты о компьютерных играх: история и технологии", "i": "🎮", "c": "igry-i-razvlecheniya"}, {"s": "interesnye-smajliki-iz-simvolov", "t": "Красивые смайлики из символов: полный список и коды", "i": "💿", "c": "soft-i-prilozheniya"}, {"s": "induktsionnaya-zaryadka-dlya-telefona", "t": "Индукционная зарядка для телефона: принцип работы, плюсы и минусы", "i": "📱", "c": "smartfony-i-planshety"}, {"s": "interesnoe-na-3d-printere", "t": "Что печатать на 3D принтере: 10 крутых идей для дома и творчества", "i": "🖨️", "c": "3d-pechat-i-modelirovanie"}, {"s": "internet-lte-chto-znachit", "t": "Интернет LTE: что это, как работает и чем отличается от 4G", "i": "📶", "c": "set-i-internet"}, {"s": "internet-ot-megafona-tarify-dlya-modema-4g-bezlimitnyj", "t": "Интернет от МегаФона тарифы для модема 4G безлимитный: выбор и настройка", "i": "📶", "c": "set-i-internet"}, {"s": "informatsiya-pro-pamyatnik-rodina-mat", "t": "Памятник «Родина-мать зовёт!»: история, размеры и факты о гиганте", "i": "📁", "c": "drugoe"}, {"s": "inogda-vyklyuchaetsya-monitor-i-vklyuchaetsya", "t": "Монитор выключается и включается: причины и решения", "i": "🖥️", "c": "kompyutery-i-noutbuki"}, {"s": "instagram-ne-daet-vosstanovit-parol", "t": "Инстаграм не дает восстановить пароль: 7 рабочих способов", "i": "🔒", "c": "bezopasnost-i-akkaunty"}, {"s": "internet-k-noutbuku-cherez-usb-modem", "t": "Как подключить интернет к ноутбуку через USB модем: Полное руководство", "i": "📶", "c": "set-i-internet"}, {"s": "interesnye-fakty-pro-chikatilo", "t": "Интересные факты про Чикатило: тайны самого кровавого маньяка", "i": "📁", "c": "drugoe"}, {"s": "indeks-v-ajfone-chto-pisat", "t": "Индекс в Айфоне: что писать и как настроить", "i": "📱", "c": "smartfony-i-planshety"}, {"s": "indikator-wan-na-routere-ne-gorit", "t": "Индикатор WAN на роутере не горит: причины и пошаговое решение", "i": "📶", "c": "set-i-internet"}, {"s": "internet-kabel-5e-i-6e-raznitsa", "t": "Кабель 5е и 6е: в чем разница и что лучше выбрать", "i": "📶", "c": "set-i-internet"}, {"s": "internet-na-dache-varianty-podklyucheniya-svoimi-rukami", "t": "Интернет на даче: варианты подключения своими руками", "i": "📶", "c": "set-i-internet"}, {"s": "interesnye-fakty-ob-aviatsii", "t": "Интересные факты об авиации: мифы, рекорды и технологии", "i": "📁", "c": "drugoe"}, {"s": "interesnye-funktsii-na-ajfone", "t": "Скрытые фишки iPhone: 10 полезных функций, о которых вы не знали", "i": "📱", "c": "smartfony-i-planshety"}, {"s": "internet-kabel-4-zhily-i-8-zhil-raznitsa", "t": "Интернет кабель 4 и 8 жил: в чем разница, скорость и выбор", "i": "📶", "c": "set-i-internet"}, {"s": "internet-radio-dlya-android-luchshie", "t": "Топ интернет радио для Android: лучшие приложения 2026 года", "i": "📱", "c": "smartfony-i-planshety"}, {"s": "instrumenty-dlya-sborki-pk", "t": "Инструменты для сборки ПК: полный гайд для домашнего мастера", "i": "🖥️", "c": "kompyutery-i-noutbuki"}, {"s": "intel-celeron-b800-apgrejd", "t": "Intel Celeron B800 апгрейд: замена на Core i3, i5 или i7", "i": "🖥️", "c": "kompyutery-i-noutbuki"}, {"s": "internal-storage-pustaya-papka-iphone-chto-delat", "t": "Internal Storage пустая папка iPhone: очистка и решение", "i": "📱", "c": "smartfony-i-planshety"}, {"s": "inogda-gasnet-monitor-na-paru-sekund", "t": "Монитор гаснет на секунду: поиск причины и ремонт", "i": "🖥️", "c": "kompyutery-i-noutbuki"}, {"s": "intel-me-system-tools", "t": "Intel ME System Tools: полное руководство по управлению ME", "i": "🖥️", "c": "kompyutery-i-noutbuki"}, {"s": "internet-antenna-dlya-dachi-s-usilitelem", "t": "Интернет антенна для дачи с усилителем: выбор и установка", "i": "📶", "c": "set-i-internet"}, {"s": "insult-blog-vitaliya-shabanova-video", "t": "Инсульт: блог Виталия Шабанова и видео-уроки по реабилитации", "i": "📁", "c": "drugoe"}, {"s": "infrakrasnyj-filtr-na-obektiv", "t": "Инфракрасный фильтр на объектив: выбор и применение", "i": "⌚", "c": "elektronika-i-gadzhety"}, {"s": "indikator-zvonka-mobilnogo-telefona", "t": "Индикатор звонка на телефоне: типы, настройки и устранение неисправностей", "i": "📱", "c": "smartfony-i-planshety"}, {"s": "internet-na-dache-varianty-podklyucheniya", "t": "Интернет на даче: лучшие варианты подключения 2026", "i": "📶", "c": "set-i-internet"}, {"s": "instruktsiya-po-ustanovke-sensornogo-vyklyuchatelya", "t": "Установка сенсорного выключателя: пошаговая инструкция", "i": "🏠", "c": "umnyj-dom"}, {"s": "informatsiya-o-zakrytoj-stranitse-vk", "t": "Закрытая страница ВК: что значит, причины блокировки и восстановление", "i": "🔒", "c": "bezopasnost-i-akkaunty"}, {"s": "instruktazhi-dlya-voditelej-transportnykh-sredstv", "t": "Инструктажи для водителей: виды, сроки, оформление по БДД", "i": "📁", "c": "drugoe"}, {"s": "intel-core-i5-3230m-apgrejd", "t": "Intel Core i5 3230M апгрейд: выбор процессора и замена", "i": "🖥️", "c": "kompyutery-i-noutbuki"}, {"s": "interesnye-rasskazy-iz-zhizni-korotkie", "t": "Короткие рассказы из жизни: лучшие истории и идеи", "i": "📁", "c": "drugoe"}, {"s": "internet-s-antennoj-i-routerom-dlya-dachi", "t": "Интернет для дачи: выбор антенны и роутера для стабильной связи", "i": "📶", "c": "set-i-internet"}, {"s": "integratsiya-kamery-v-home-assistant", "t": "Как добавить камеру в Home Assistant: Полное руководство по интеграции", "i": "🏠", "c": "umnyj-dom"}, {"s": "intel-core-i3-380m-apgrejd", "t": "Intel Core i3-380M: Апгрейд ноутбука, замена на i5 и i7", "i": "🖥️", "c": "kompyutery-i-noutbuki"}, {"s": "intel-hm70-podderzhivaemye-protsessory", "t": "Intel HM70 поддерживаемые процессоры: список совместимости", "i": "🖥️", "c": "kompyutery-i-noutbuki"}, {"s": "internet-ne-rabotaet-pri-zvonke", "t": "Интернет не работает при звонке: почему и как исправить связь", "i": "📶", "c": "set-i-internet"}, {"s": "internet-tinkoff-plokho-gruzit-chto-delat", "t": "Тинькофф не грузит: почему и что делать", "i": "📶", "c": "set-i-internet"}, {"s": "internet-tsentr-yota-2-otzyvy", "t": "Интернет центр Yota 2: отзывы, характеристики и настройка", "i": "📶", "c": "set-i-internet"}, {"s": "instruktsiya-po-naklejke-plenki-na-telefon", "t": "Как правильно наклеить защитную пленку на телефон: пошаговая инструкция", "i": "📱", "c": "smartfony-i-planshety"}, {"s": "internet-na-dache-cherez-sim-kartu", "t": "Интернет на даче через сим-карту: выбор, настройка, усиление", "i": "📶", "c": "set-i-internet"}, {"s": "indeks-dlya-apple-id", "t": "Индекс для Apple ID: что это и как его использовать для аккаунта", "i": "🔒", "c": "bezopasnost-i-akkaunty"}, {"s": "intellektualnyj-uroven-snaryada-vesom-9-gramm-krossvord", "t": "Интеллектуальный уровень снаряда 9 грамм: кроссворд и факты", "i": "📁", "c": "drugoe"}, {"s": "initsializatsiya-ssd-diska-v-windows-10", "t": "Инициализация SSD диска в Windows 10: пошаговая инструкция", "i": "🖥️", "c": "kompyutery-i-noutbuki"}, {"s": "instrument-vedenie-v-sketchup", "t": "Инструмент Ведение в SketchUp: Полное руководство по настройке", "i": "🖨️", "c": "3d-pechat-i-modelirovanie"}, {"s": "internet-gde-net-mobilnoj-svyazi", "t": "Как получить интернет без мобильной связи: спутник, спутниковый роутер и офлайн-карты", "i": "📶", "c": "set-i-internet"}, {"s": "internet-napryamuyu-bez-routera", "t": "Как подключить интернет напрямую без роутера: способы и нюансы", "i": "📶", "c": "set-i-internet"}, {"s": "initsializatsiya-diskov-mbr-ili-gpt-dlya-ssd", "t": "Инициализация SSD: MBR или GPT — правильный выбор", "i": "🖥️", "c": "kompyutery-i-noutbuki"}, {"s": "internet-kabel-pokhozh-na-telefonnyj-no-s-bolee-krupnymi-razemami-na-kontsakh-chto-delat", "t": "Какой кабель использовать: Ethernet или телефонный? Как отличить и подключить", "i": "📶", "c": "set-i-internet"}, {"s": "internet-v-selskoj-mestnosti", "t": "Интернет в сельской местности: выбор, подключение и проблемы", "i": "📶", "c": "set-i-internet"}, {"s": "informatsiya-o-cheloveke-po-pasportnym-dannym", "t": "Что можно узнать о человеке по паспортным данным: реальные риски", "i": "🔒", "c": "bezopasnost-i-akkaunty"}, {"s": "innbox-e80-proshivka-rostelekom", "t": "Innbox E80 прошивка Ростелеком: обновление и сброс", "i": "📺", "c": "televizory-i-tv-pristavki"}, {"s": "internet-brauzer-dlya-windows-xp", "t": "Лучшие интернет браузеры для Windows XP в 2026 году: обзор и установка", "i": "🖥️", "c": "kompyutery-i-noutbuki"}, {"s": "internet-na-dachu-svoimi-rukami-poshagovo", "t": "Интернет на дачу своими руками: пошаговая инструкция", "i": "📶", "c": "set-i-internet"}, {"s": "instruktsiya-po-naklejke-zashchitnogo-stekla-na-smartfon", "t": "Как наклеить защитное стекло на смартфон: пошаговая инструкция", "i": "📱", "c": "smartfony-i-planshety"}, {"s": "internet-na-dachu-cherez-sim-kartu", "t": "Интернет на дачу через сим-карту: выбор оборудования и тарифов", "i": "📶", "c": "set-i-internet"}, {"s": "innbox-e80-nastrojka-rostelekom", "t": "Настройка приставки Innbox E80 для Ростелеком: пошаговая инструкция", "i": "📶", "c": "set-i-internet"}, {"s": "input-5v-2a-chto-eto-znachit", "t": "Input 5V 2A: что это значит и как выбрать адаптер", "i": "⌚", "c": "elektronika-i-gadzhety"}, {"s": "internet-na-dache-kakoe-oborudovanie-nado-kupit", "t": "Интернет на даче: какое оборудование купить в 2026 году", "i": "📶", "c": "set-i-internet"}, {"s": "internet-rabotaet-no-ne-gruzit-stranitsy", "t": "Интернет работает, но не грузит страницы: причины и быстрое решение", "i": "📶", "c": "set-i-internet"}, {"s": "inn-fizicheskogo-litsa-uznat-po-familii", "t": "Как узнать ИНН физического лица по фамилии и другим данным онлайн", "i": "🔒", "c": "bezopasnost-i-akkaunty"}, {"s": "instruktazhi-voditelej-po-bezopasnosti-dorozhnogo-dvizheniya", "t": "Инструктажи водителей: виды, периодичность и протокол по безопасности", "i": "🚗", "c": "avtomobilnaya-elektronika"}, {"s": "integratsiya-alisy-v-home-assistant", "t": "Интеграция Алисы в Home Assistant: полное руководство 2026", "i": "🏠", "c": "umnyj-dom"}, {"s": "invalid-conversion-from-const-char-to-char", "t": "Ошибка invalid conversion from const char* to char*: Решения на C++", "i": "💿", "c": "soft-i-prilozheniya"}, {"s": "indikator-aktivnosti-zhestkogo-diska", "t": "Индикатор активности жесткого диска: что значит и как исправить", "i": "🖥️", "c": "kompyutery-i-noutbuki"}, {"s": "instrumenty-dlya-3d-printera", "t": "Лучшие инструменты для 3D принтера: полный список", "i": "🖨️", "c": "3d-pechat-i-modelirovanie"}, {"s": "indeks-dlya-epl-ajdi", "t": "Индекс для Apple ID: что это и как проверить", "i": "📱", "c": "smartfony-i-planshety"}, {"s": "infinix-proizvoditel-chto-za-brend", "t": "Infinix: Кто производитель и что за бренд смартфонов? Обзор 2026", "i": "📱", "c": "smartfony-i-planshety"}, {"s": "internavi-linc-premium-club-fleshka-chto-eto", "t": "ИнтерНави Линк Премиум Клуб флешка: что это, обновление и особенности", "i": "🚗", "c": "avtomobilnaya-elektronika"}, {"s": "intel-hm55-express-podderzhivaemye-protsessory", "t": "Процессоры для Intel HM55 Express: полный список и совместимость", "i": "🖥️", "c": "kompyutery-i-noutbuki"}, {"s": "interfejs-spi-chto-eto", "t": "SPI интерфейс: Что это, принцип работы и применение в электронике", "i": "🖥️", "c": "kompyutery-i-noutbuki"}, {"s": "internet-ot-sim-karty-dlya-doma", "t": "Интернет от SIM-карты для дома: выбор роутера, тарифы и настройка", "i": "📶", "c": "set-i-internet"}, {"s": "interny-2-sezon-34-seriya", "t": "Интерны 2 сезон 34 серия: Сюжет, герои и главные моменты выпуска", "i": "🎧", "c": "audio-i-video"}, {"s": "informatsiya-o-pamyatnike-rodina-mat", "t": "Памятник Родина-мать: история, факты и реставрация", "i": "📁", "c": "drugoe"}, {"s": "instruktsiya-po-proshivke-xiaomi", "t": "Инструкция по прошивке Xiaomi: все способы и риски", "i": "📱", "c": "smartfony-i-planshety"}, {"s": "interesnye-znachki-dlya-teksta", "t": "Как добавить интересные значки и эмодзи в текст: лучшие символы и методы", "i": "💿", "c": "soft-i-prilozheniya"}, {"s": "internet-po-antennomu-kabelyu", "t": "Интернет по антенному кабелю: технология, настройки и подвохи", "i": "📶", "c": "set-i-internet"}, {"s": "instruktsiya-po-ustanovke-vasya-diagnost", "t": "Инструкция по установке Вася Диагност: пошаговый гайд", "i": "🚗", "c": "avtomobilnaya-elektronika"}, {"s": "interesnye-mekhanizmy-na-3d-printere", "t": "Топ интересных механизмов на 3D принтере: от шестерен до роботов", "i": "🖨️", "c": "3d-pechat-i-modelirovanie"}, {"s": "intel-core-i7-620m-kharakteristiki", "t": "Intel Core i7 620M характеристики, тесты и совместимость", "i": "🖥️", "c": "kompyutery-i-noutbuki"}, {"s": "interfejs-i-protokol-raznitsa", "t": "Интерфейс и протокол: в чем разница простыми словами", "i": "📶", "c": "set-i-internet"}, {"s": "intel-core-i3-2370m-apgrejd", "t": "Intel Core i3-2370M: Апгрейд ноутбука и замена процессора", "i": "🖥️", "c": "kompyutery-i-noutbuki"}, {"s": "instruktsiya-k-bortovomu-kompyuteru-shtat", "t": "Полная инструкция к бортовому компьютеру ШТАТ: настройка и функции", "i": "🚗", "c": "avtomobilnaya-elektronika"}, {"s": "internet-dlya-noutbuka-v-doroge", "t": "Интернет для ноутбука в дороге: Wi-Fi, 4G и роуминг", "i": "📶", "c": "set-i-internet"}, {"s": "internet-radio-dlya-android-avto", "t": "Лучшее интернет-радио для Android Auto: Обзор приложений и настройка", "i": "🚗", "c": "avtomobilnaya-elektronika"}, {"s": "instrument-na-3d-printere", "t": "Инструмент на 3D принтере: какие нужны для работы", "i": "🖨️", "c": "3d-pechat-i-modelirovanie"}, {"s": "interesnye-shrifty-dlya-nika", "t": "Интересные шрифты для ника: генераторы, готика и кириллица", "i": "💿", "c": "soft-i-prilozheniya"}, {"s": "internet-filtr-keenetic-kakoj-vybrat", "t": "Интернет фильтр Keenetic: какой выбрать и настроить", "i": "📶", "c": "set-i-internet"}, {"s": "internet-radio-prilozhenie-dlya-android", "t": "Топ приложений интернет-радио для Android: выбор и настройка", "i": "💿", "c": "soft-i-prilozheniya"}, {"s": "internet-dlya-avtomobilya-kakoj-tarif-vybrat", "t": "Интернет для автомобиля: какой тариф и модем выбрать", "i": "📶", "c": "set-i-internet"}, {"s": "internet-dlya-dachi-sim-karta", "t": "Интернет для дачи через сим-карту: выбор оператора и роутера", "i": "📶", "c": "set-i-internet"}, {"s": "internet-est-no-ne-otkryvaet-stranitsy", "t": "Интернет есть, но страницы не открываются: причины и решения", "i": "📶", "c": "set-i-internet"}]