[{"s": "schetchik-s-sim-kartoj", "t": "Счетчик с сим-картой: выбор, настройка и тарифы 2026", "i": "🏠", "c": "umnyj-dom"}, {"s": "scp-na-udalennyj-server", "t": "Перенос файлов через SCP на удаленный сервер: Полное руководство", "i": "📶", "c": "set-i-internet"}, {"s": "scan-tool-pro-otzyvy", "t": "Scan Tool Pro отзывы: реальный опыт, возможности и недостатки", "i": "🚗", "c": "avtomobilnaya-elektronika"}, {"s": "scx-4300-sbros-schetchika-tonera", "t": "Сброс счетчика тонера Samsung SCX 4300: Инструкция и нюансы", "i": "🖨️", "c": "printery-i-periferiya"}, {"s": "schitaetsya-li-zapis-na-diktofon-dokazatelstvom-v-sude", "t": "Является ли запись на диктофон доказательством в суде РФ", "i": "📁", "c": "drugoe"}, {"s": "scx-4220-zamyatie-bumagi", "t": "SCX-4220 замятие бумаги: причины, коды ошибок и ремонт", "i": "🖨️", "c": "printery-i-periferiya"}, {"s": "scp-skopirovat-papku-s-soderzhimym", "t": "SCP скопировать папку с содержимым: полная инструкция", "i": "📶", "c": "set-i-internet"}, {"s": "screen-mirroring-kak-podklyuchit-ajfon", "t": "Screen Mirroring: Как подключить iPhone к телевизору и проектору", "i": "📱", "c": "smartfony-i-planshety"}, {"s": "scanmatik-2-pro-programmy", "t": "Программы для Scanmatik 2 Pro: обзор, настройка и обновление", "i": "🚗", "c": "avtomobilnaya-elektronika"}, {"s": "scrlk-na-klaviature-chto-eto", "t": "Клавиша Scrlk на клавиатуре: что это, функции и как отключить", "i": "🖥️", "c": "kompyutery-i-noutbuki"}, {"s": "schastlivye-lyudi-film-smotret-onlajn-besplatno-v-khoroshem-kachestve", "t": "Фильм Счастливые люди: где смотреть онлайн, обзор и характеристики", "i": "🎧", "c": "audio-i-video"}, {"s": "scanmaster-elm-skachat-torrent", "t": "Scanmaster ELM: где скачать безопасно и легально", "i": "🚗", "c": "avtomobilnaya-elektronika"}, {"s": "schastlivye-lyudi-dokumentalnyj-film-enisej-2-seriya", "t": "Документальный фильм Счастливые люди 2 серия: суть, анализ и герои", "i": "🎧", "c": "audio-i-video"}, {"s": "schityvanie-nfc-metki-telefonom", "t": "Как считать NFC метку телефоном: полная инструкция", "i": "📱", "c": "smartfony-i-planshety"}, {"s": "scp-from-remote-to-local", "t": "SCP Remote to Local: Копирование файлов в Linux за 5 минут", "i": "📶", "c": "set-i-internet"}, {"s": "scp-linux-to-linux", "t": "Как передать файлы по SCP с Linux на Linux: полное руководство", "i": "🖥️", "c": "kompyutery-i-noutbuki"}, {"s": "schitat-dannye-s-zhestkogo-diska", "t": "Как считать данные с жесткого диска: восстановление и диагностика", "i": "🔧", "c": "remont-i-diagnostika"}, {"s": "scp-kopirovanie-fajlov-s-udalennogo-servera", "t": "SCP копирование файлов: как скачать и загрузить на сервер", "i": "📶", "c": "set-i-internet"}, {"s": "screen-mirroring-chto-eto", "t": "Screen Mirroring: что это, как работает и чем отличается от Chromecast", "i": "📺", "c": "televizory-i-tv-pristavki"}, {"s": "schitat-nfc-metku-na-telefon", "t": "Как считать NFC метку на телефон: полное руководство", "i": "📱", "c": "smartfony-i-planshety"}, {"s": "scanmaster-elm327-na-russkom-skachat-besplatno-dlya-windows-10-64-bit", "t": "ScanMaster ELM327 на русском: скачать бесплатно для Windows 10 64 bit", "i": "🚗", "c": "avtomobilnaya-elektronika"}, {"s": "scanmatik-skachat-dlya-android", "t": "Scanmatik скачать для Android: инструкции, риски и работа с OBD2", "i": "🚗", "c": "avtomobilnaya-elektronika"}, {"s": "screen-2-auto-skachat-apk", "t": "Screen 2 Auto скачать APK: Полная инструкция по установке и настройке", "i": "🚗", "c": "avtomobilnaya-elektronika"}, {"s": "scx-4200-net-tonera", "t": "Samsung SCX-4200 нет тонера: решение проблемы мигания индикатора", "i": "🖨️", "c": "printery-i-periferiya"}, {"s": "scp-kak-skopirovat-papku", "t": "scp как скопировать папку: Полная инструкция по передаче данных", "i": "📶", "c": "set-i-internet"}, {"s": "scp-linux-skopirovat-papku", "t": "SCP Linux скопировать папку: полная инструкция и примеры", "i": "📶", "c": "set-i-internet"}, {"s": "scan-tool-pro-2019", "t": "Scan Tool Pro 2019: Обзор функций и диагностика авто", "i": "🚗", "c": "avtomobilnaya-elektronika"}, {"s": "screen-mirroring-kak-nastroit", "t": "Как настроить Screen Mirroring: инструкция для Android, iOS и Smart TV", "i": "📺", "c": "televizory-i-tv-pristavki"}, {"s": "screen-mirroring-kak-podklyuchit", "t": "Screen Mirroring: как подключить телефон к телевизору", "i": "📺", "c": "televizory-i-tv-pristavki"}, {"s": "schastlivoe-vremya-na-chasakh-kakoe", "t": "Счастливое время на часах: значение и приметы", "i": "📁", "c": "drugoe"}, {"s": "screen-2-auto-skachat-dlya-android", "t": "Screen2Auto для Android: Скачать, установить и настроить CarPlay", "i": "🚗", "c": "avtomobilnaya-elektronika"}, {"s": "screen-2-auto-nastrojka", "t": "Screen 2 auto настройка: полный гайд по калибровке", "i": "📺", "c": "televizory-i-tv-pristavki"}, {"s": "scan-tool-pro-prilozhenie-dlya-android", "t": "Scan Tool Pro для Android: Полный обзор диагностического сканера", "i": "🚗", "c": "avtomobilnaya-elektronika"}, {"s": "scp-linux-to-windows", "t": "Как передать файлы с Linux на Windows через SCP: Полное руководство", "i": "📶", "c": "set-i-internet"}, {"s": "screen-mirroring-kak-polzovatsya", "t": "Screen Mirroring: Как настроить дублирование экрана на Android, iPhone и ПК", "i": "📺", "c": "televizory-i-tv-pristavki"}, {"s": "schastlivye-lyudi-dokumentalnyj-film-2-seriya", "t": "Счастливые люди (документальный фильм): обзор 2 серии, где смотреть и анализ сюжета", "i": "🎧", "c": "audio-i-video"}, {"s": "scanmatik-2-pro-skachat", "t": "Scanmatik 2 Pro скачать: драйверы, прошивка и установка ПО", "i": "🚗", "c": "avtomobilnaya-elektronika"}, {"s": "schitat-nfs-metku-telefonom", "t": "Как считать NFC-метку телефоном: полная инструкция 2026", "i": "📱", "c": "smartfony-i-planshety"}, {"s": "scp-skachat-fajl-s-servera", "t": "Как скачать файл с сервера через SCP: полная инструкция", "i": "📶", "c": "set-i-internet"}, {"s": "scanmatik-ru-android-skachat", "t": "Scanmatik для Android: скачать, установка и настройка сканера", "i": "🚗", "c": "avtomobilnaya-elektronika"}]