[{"s": "so-skolkikh-chasov-nachinaetsya-noch", "t": "Во сколько начинается ночь: астрономические и бытовые нормы", "i": "🏠", "c": "umnyj-dom"}, {"s": "sony-ericsson-knopochnyj-telefon", "t": "Sony Ericsson кнопочный телефон: обзор, ремонт и лучшие модели", "i": "📱", "c": "smartfony-i-planshety"}, {"s": "sony-ericsson-raskladushka-vse-modeli", "t": "Все модели раскладушек Sony Ericsson: обзор и характеристики", "i": "📱", "c": "smartfony-i-planshety"}, {"s": "sony-ericsson-vse-modeli-telefonov-po-godam", "t": "Модели телефонов Sony Ericsson: полная хронология и список по годам", "i": "📱", "c": "smartfony-i-planshety"}, {"s": "sony-ericsson-express-music", "t": "Sony Ericsson Walkman и Express Music: история и отличия", "i": "⌚", "c": "elektronika-i-gadzhety"}, {"s": "sopryazhenie-mavik-3-s-pultom", "t": "Сопряжение DJI Mavic 3 с пультом DJI RC: полная инструкция", "i": "⌚", "c": "elektronika-i-gadzhety"}, {"s": "sobesednik-plokho-slyshit-menya-po-telefonu-android", "t": "Собеседник плохо слышит по телефону: решение на Android", "i": "📱", "c": "smartfony-i-planshety"}, {"s": "sobrat-byudzhetnyj-igrovoj-pk", "t": "Как собрать бюджетный игровой ПК: Полный гайд 2026", "i": "🖥️", "c": "kompyutery-i-noutbuki"}, {"s": "sokhranit-video-s-yandeks-dzen", "t": "Как сохранить видео с Яндекс Дзен: 5 рабочих способов 2026", "i": "💿", "c": "soft-i-prilozheniya"}, {"s": "sotovye-dannye-nedostupny-vo-vremya-etogo-vyzova", "t": "Сотовые данные недоступны во время вызова: причины и решения", "i": "📱", "c": "smartfony-i-planshety"}, {"s": "sochetanie-klavish-pokazat-rabochij-stol", "t": "Как быстро показать рабочий стол: горячие клавиши и методы для Windows", "i": "🖥️", "c": "kompyutery-i-noutbuki"}, {"s": "sozdat-akkaunt-rebenku-na-ajfon", "t": "Как создать аккаунт ребенку на Айфон: инструкция для родителей", "i": "📱", "c": "smartfony-i-planshety"}, {"s": "so-skolki-vremeni-noch", "t": "Со скольки начинается ночь: официальное время и нормы", "i": "📁", "c": "drugoe"}, {"s": "so-skolki-vremeni-schitaetsya-vecher", "t": "Со скольки времени начинается вечер: нормы, биоритмы и юридические аспекты", "i": "🏠", "c": "umnyj-dom"}, {"s": "sochetanie-klavish-chtoby-vyrezat-tekst", "t": "Сочетание клавиш чтобы вырезать текст: инструкции для Windows и Mac", "i": "🖥️", "c": "kompyutery-i-noutbuki"}, {"s": "sovpadenie-chisel-na-chasakh-15-15", "t": "Совпадение чисел на часах 15:15: Значение, нумерология и психология", "i": "📁", "c": "drugoe"}, {"s": "sozdanie-vnutrennej-rezby-v-kompas-3d", "t": "Как создать внутреннюю резьбу в Компас 3D: Пошаговая инструкция", "i": "🖨️", "c": "3d-pechat-i-modelirovanie"}, {"s": "soni-erikson-telefon-sensornyj-vse-modeli", "t": "Все сенсорные телефоны Sony Ericsson: обзор моделей и особенности", "i": "📱", "c": "smartfony-i-planshety"}, {"s": "sovmestimost-libreoffice-i-microsoft-office", "t": "Совместимость LibreOffice и Microsoft Office: полное руководство", "i": "💿", "c": "soft-i-prilozheniya"}, {"s": "so-skolki-i-do-skolki-dlitsya-den", "t": "Со скольки и до скольки длится день: астрономия и законы", "i": "📁", "c": "drugoe"}, {"s": "sochetanie-klavish-dlya-otmeny-poslednego-dejstviya", "t": "Горячие клавиши для отмены действий: Universal Undo Guide", "i": "💿", "c": "soft-i-prilozheniya"}, {"s": "sokhranyaetsya-li-nomer-telefona-pri-smene-operatora", "t": "Сохраняется ли номер телефона при смене оператора: правила переноса MNP", "i": "📶", "c": "set-i-internet"}, {"s": "soni-erikson-t-230", "t": "Sony Ericsson T230: Обзор легендарного кнопочного телефона 2002 года", "i": "📱", "c": "smartfony-i-planshety"}, {"s": "sochetanie-klavish-svojstva-fajla", "t": "Сочетание клавиш свойства файла: Alt+Enter и аналоги", "i": "🖥️", "c": "kompyutery-i-noutbuki"}, {"s": "sodimm-ddr3-i-ddr3l-razlichie", "t": "SODIMM DDR3 и DDR3L: ключевые различия и совместимость", "i": "🖥️", "c": "kompyutery-i-noutbuki"}, {"s": "sochetanie-klavish-dlya-perekhoda-na-rabochij-stol", "t": "Сочетание клавиш для перехода на рабочий стол: Windows и Mac", "i": "🖥️", "c": "kompyutery-i-noutbuki"}, {"s": "soedinenie-dvukh-routerov-kabelem-v-odnu-set", "t": "Соединение двух роутеров в одну сеть кабелем: пошаговая инструкция", "i": "📶", "c": "set-i-internet"}, {"s": "soni-erikson-raskladushka-starye-modeli", "t": "Сони Эриксон раскладушка: старые модели, характеристики и цены", "i": "⌚", "c": "elektronika-i-gadzhety"}, {"s": "sotovye-telefony-90kh-godov", "t": "Сотовые телефоны 90-х годов: история, модели и технологии эпохи", "i": "📱", "c": "smartfony-i-planshety"}, {"s": "sovetskij-bukvar-skachat-besplatno-1976", "t": "Советский букварь 1976 года: скачать бесплатно и распечатать", "i": "💿", "c": "soft-i-prilozheniya"}, {"s": "sozdat-obraz-sistemy-windows-7", "t": "Как создать образ системы Windows 7: полная инструкция", "i": "🖥️", "c": "kompyutery-i-noutbuki"}, {"s": "sobesednik-ne-slyshit-menya-v-telefone-iphone", "t": "Собеседник не слышит в iPhone: причины, чистка и настройки микрофона", "i": "📱", "c": "smartfony-i-planshety"}, {"s": "sovpadayushchee-vremya-na-chasakh", "t": "Совпадающее время на часах: значение, поверья и как настроить", "i": "⌚", "c": "elektronika-i-gadzhety"}, {"s": "sozdat-lokalnuyu-set-onlajn", "t": "Как создать локальную сеть онлайн: виртуальные сети и настройки", "i": "📶", "c": "set-i-internet"}, {"s": "solnechnaya-batareya-dlya-zaryadki-telefona", "t": "Солнечная батарея для зарядки телефона: выбор и обзор", "i": "⌚", "c": "elektronika-i-gadzhety"}, {"s": "sonet-130-shekspir-original", "t": "Сонет 130 Шекспир: оригинал на английском с переводом и анализом", "i": "⌚", "c": "elektronika-i-gadzhety"}, {"s": "sokhranit-video-iz-dzen", "t": "Как сохранить видео из Дзен: все способы и программы", "i": "💿", "c": "soft-i-prilozheniya"}, {"s": "solid-vorks-flow-simulation", "t": "SolidWorks Flow Simulation: руководство по настройке и расчетам CFD", "i": "🖨️", "c": "3d-pechat-i-modelirovanie"}, {"s": "sony-ericsson-linejka-telefonov", "t": "Линейки телефонов Sony Ericsson: история, модели и легендарные новинки", "i": "📱", "c": "smartfony-i-planshety"}, {"s": "sotovaya-svyaz-ne-lovit", "t": "Почему не ловит сотовая связь: причины и что делать", "i": "📱", "c": "smartfony-i-planshety"}, {"s": "sozdanie-apple-id-dlya-rebenka", "t": "Создание Apple ID для ребенка: инструкция и настройки", "i": "📱", "c": "smartfony-i-planshety"}, {"s": "sozdanie-obraza-ssd-diska", "t": "Создание образа SSD диска: полная инструкция по клонированию и бэкапу", "i": "🖥️", "c": "kompyutery-i-noutbuki"}, {"s": "sozdanie-zagruzochnoj-fleshki-macos", "t": "Как создать загрузочную флешку macOS: полное руководство 2026", "i": "🖥️", "c": "kompyutery-i-noutbuki"}, {"s": "sozdat-uchetnuyu-zapis-apple-id-na-telefone", "t": "Как создать Apple ID на телефоне: полная инструкция 2026", "i": "📱", "c": "smartfony-i-planshety"}, {"s": "sony-vaio-control-center", "t": "Sony VAIO Control Center: установка, настройка и решение проблем", "i": "🖥️", "c": "kompyutery-i-noutbuki"}, {"s": "sony-xperia-ear-duo", "t": "Sony Xperia Ear Duo: Инновационные наушники открытого типа", "i": "🎧", "c": "audio-i-video"}, {"s": "sovpadenie-chisel-na-chasakh-i-ikh-znachenie", "t": "Совпадение чисел на часах: значение зеркальных и повторяющихся цифр", "i": "📁", "c": "drugoe"}, {"s": "sochetanie-klavish-svernut-okno", "t": "Как свернуть окно: сочетания клавиш для Windows и Mac", "i": "🖥️", "c": "kompyutery-i-noutbuki"}, {"s": "soni-erikson-sensornyj-staryj", "t": "Сони Эриксон сенсорный: обзор легендарных моделей и ремонт", "i": "📱", "c": "smartfony-i-planshety"}, {"s": "sovpadenie-chisel-na-chasakh-21-21", "t": "21:21 на часах: эзотерическое значение и психология синхронистичности", "i": "🏠", "c": "umnyj-dom"}, {"s": "sochetanie-klavish-dlya-poiska-v-vorde", "t": "Сочетание клавиш для поиска в Ворде: все команды", "i": "💿", "c": "soft-i-prilozheniya"}, {"s": "soglasie-na-zapis-razgovora-na-diktofon", "t": "Согласие на запись разговора на диктофон: законность и нюансы", "i": "🔒", "c": "bezopasnost-i-akkaunty"}, {"s": "sozdanie-zagruzochnoj-fleshki-mac-os-sierra", "t": "Как создать загрузочную флешку macOS Sierra: полная инструкция", "i": "🖥️", "c": "kompyutery-i-noutbuki"}, {"s": "sochetanie-klavish-na-rabochij-stol", "t": "Сочетание клавиш для быстрого возврата на Рабочий стол в Windows", "i": "🖥️", "c": "kompyutery-i-noutbuki"}, {"s": "sovetskie-voennye-karty-prilozhenie-dlya-android", "t": "Советские военные карты на Android: Топ приложений и способы загрузки", "i": "📱", "c": "smartfony-i-planshety"}, {"s": "sochetanie-klavish-dejstvie-vpered", "t": "Комбинация клавиш «Действие вперед»: горячие клавиши для возврата и повтора", "i": "🖥️", "c": "kompyutery-i-noutbuki"}, {"s": "sochetanie-klavish-zakryt-dokument", "t": "Сочетание клавиш для закрытия документа: полное руководство", "i": "💿", "c": "soft-i-prilozheniya"}, {"s": "solnechnye-batarei-dlya-telefona", "t": "Солнечные батареи для телефона: обзор зарядок, эффективность и выбор", "i": "📱", "c": "smartfony-i-planshety"}, {"s": "sotovye-vyshki-ryadom-so-mnoj", "t": "Как найти сотовые вышки рядом со мной: карты, приложения и частоты", "i": "📶", "c": "set-i-internet"}, {"s": "sozdanie-domashnej-seti-cherez-router", "t": "Создание домашней сети через роутер: пошаговая настройка Wi-Fi", "i": "📶", "c": "set-i-internet"}, {"s": "soft-dlya-android-tv", "t": "Лучший софт для Андроид ТВ: ТОП приложений и утилит 2026", "i": "📺", "c": "televizory-i-tv-pristavki"}, {"s": "solnechnaya-panel-dlya-pokhoda-kakuyu-vybrat", "t": "Как выбрать солнечную панель для похода: гид по мощности и типу", "i": "⌚", "c": "elektronika-i-gadzhety"}, {"s": "sound-blaster-pro-gaming", "t": "Sound Blaster Pro Gaming: обзор звуковых карт для киберспорта", "i": "🎧", "c": "audio-i-video"}, {"s": "sozdat-svoj-simvol-dlya-teksta", "t": "Как создать свой символ для текста: шрифты и коды", "i": "💿", "c": "soft-i-prilozheniya"}, {"s": "sobesednik-plokho-slyshit-menya-po-telefonu-iphone", "t": "Плохо слышно на iPhone во время звонка: причины и решения", "i": "📱", "c": "smartfony-i-planshety"}, {"s": "so-skolki-chasov-nastupaet-utro", "t": "Со скольки часов начинается утро? Точное время и юридические нормы", "i": "📁", "c": "drugoe"}, {"s": "sozvanimsya-ili-sozvonimsya-kak-pravilno", "t": "Созванимся или созвонимся: как правильно писать и почему", "i": "📁", "c": "drugoe"}, {"s": "soedinenie-routerov-mezhdu-soboj-kabelem", "t": "Как соединить два роутера кабелем: схемы, настройка и плюсы метода", "i": "📶", "c": "set-i-internet"}, {"s": "sonet-130-eyo-glaza-na-zvyozdy-ne-pokhozhi-samuil-marshak-tekst", "t": "Сонет 130 Шекспира: анализ перевода Маршака", "i": "📁", "c": "drugoe"}, {"s": "sobrat-sistemnyj-blok-dlya-kompyutera", "t": "Как собрать системный блок: пошаговая инструкция по выбору и монтажу ПК", "i": "🖥️", "c": "kompyutery-i-noutbuki"}, {"s": "sochetanie-klavish-s-alt", "t": "Сочетания клавиш с Alt: полный список горячих клавиш для Windows", "i": "🖥️", "c": "kompyutery-i-noutbuki"}, {"s": "sovpadenie-vremeni-na-chasakh-znachenie", "t": "Совпадение времени на часах: значение и толкование", "i": "📁", "c": "drugoe"}, {"s": "sozdanie-ringtona-v-garageband", "t": "Как сделать рингтон в GarageBand на iPhone: Полная инструкция", "i": "📱", "c": "smartfony-i-planshety"}, {"s": "sozdat-eshche-odnu-stranitsu-v-kontakte", "t": "Как создать вторую страницу ВКонтакте: пошаговая инструкция и правила", "i": "📶", "c": "set-i-internet"}, {"s": "sony-wf-1000xm4-4pda", "t": "Sony WF-1000XM4: Обзор, Прошивка и Форум 4PDA", "i": "🎧", "c": "audio-i-video"}, {"s": "soobshchestvo-lyudej-i-mashin", "t": "Сообщество людей и машин: симбиоз, риски и будущее технологий", "i": "🏠", "c": "umnyj-dom"}, {"s": "sobrat-pk-do-60k", "t": "Сборка игрового ПК до 60 тысяч рублей: лучшие конфиги 2026", "i": "🖥️", "c": "kompyutery-i-noutbuki"}, {"s": "sochetanie-klavish-strelka-vverkh", "t": "Сочетание клавиш стрелка вверх: все комбинации для ПК и Mac", "i": "🖥️", "c": "kompyutery-i-noutbuki"}, {"s": "so-skolki-nastupaet-utro", "t": "Со скольки наступает утро: астрономическое и бытовое время", "i": "🏠", "c": "umnyj-dom"}, {"s": "sochetanie-klavish-dejstvie-nazad", "t": "Горячие клавиши «Назад»: Полный гайд по сочетаниям для Windows, macOS и Android", "i": "🖥️", "c": "kompyutery-i-noutbuki"}, {"s": "sozdat-lokalnuyu-set-mezhdu-dvumya-kompyuterami", "t": "Создать локальную сеть между двумя компьютерами: пошаговая инструкция", "i": "📶", "c": "set-i-internet"}, {"s": "so-skolki-nastupaet-noch", "t": "Со скольки наступает ночь: астрономия, законы и правила для гаджетов", "i": "🏠", "c": "umnyj-dom"}, {"s": "sotovyj-telefon-s-diskovym-naborom", "t": "Сотовый телефон с дисковым набором: миф или реальность?", "i": "📱", "c": "smartfony-i-planshety"}, {"s": "sovetskie-plakaty-o-vojne", "t": "Советские военные плакаты: Искусство, История и Графика Победы", "i": "🎧", "c": "audio-i-video"}, {"s": "sovremennye-kompyutery-i-ikh-kharakteristiki", "t": "Современные компьютеры: характеристики, выбор и актуальные тренды 2026", "i": "🖥️", "c": "kompyutery-i-noutbuki"}, {"s": "sochetanie-klavish-dlya-vyrezaniya-teksta", "t": "Сочетание клавиш для вырезания текста: Полная шпаргалка (Windows, Mac, Linux)", "i": "🖥️", "c": "kompyutery-i-noutbuki"}, {"s": "sovetskie-naushniki-tds-3", "t": "Советские наушники ТДС-3: обзор, характеристики и ремонт легендарной модели", "i": "🎧", "c": "audio-i-video"}, {"s": "so-skolki-do-skolki-noch-po-vremeni", "t": "Со скольки до скольки считается ночь: время, тарифы и правила", "i": "🏠", "c": "umnyj-dom"}, {"s": "sochetanie-klavish-dlya-zakrytiya-okna", "t": "Сочетание клавиш для закрытия окна: Полный гид по Windows и Mac", "i": "🖥️", "c": "kompyutery-i-noutbuki"}, {"s": "sotovyj-telefon-s-televizorom", "t": "Сотовый телефон с телевизором: как смотреть TV на смартфоне", "i": "📱", "c": "smartfony-i-planshety"}, {"s": "sozdat-detskuyu-uchetnuyu-zapis-apple", "t": "Как создать детскую учетную запись Apple: инструкция", "i": "🔒", "c": "bezopasnost-i-akkaunty"}, {"s": "sobesednik-ne-slyshit-menya-v-telefone", "t": "Собеседник не слышит меня в телефоне: причины и ремонт", "i": "📱", "c": "smartfony-i-planshety"}, {"s": "sobiraem-sistemnyj-blok-svoimi-rukami", "t": "Как собрать системный блок своими руками: пошаговая инструкция 2026", "i": "🖥️", "c": "kompyutery-i-noutbuki"}, {"s": "solnechnaya-panel-na-ryukzak", "t": "Солнечная панель на рюкзак: выбор и установка", "i": "⌚", "c": "elektronika-i-gadzhety"}, {"s": "soobshchit-o-spame-bilajn", "t": "Как сообщить о спаме Билайн: 5 способов блокировки и жалоб", "i": "📶", "c": "set-i-internet"}, {"s": "sovetskie-voennye-karty-4pda", "t": "Советские военные карты на 4PDA: поиск, форматы и 3D-примеры", "i": "💿", "c": "soft-i-prilozheniya"}, {"s": "sovokupnost-shiny-dannykh-shiny-upravleniya-i-shiny-adresov-nazyvaetsya-ili-magistralyu", "t": "Что такое системная шина: виды, назначение и принцип работы", "i": "🖥️", "c": "kompyutery-i-noutbuki"}, {"s": "sozdanie-uefi-zagruzochnoj-fleshki-windows-10", "t": "Создание UEFI загрузочной флешки Windows 10: пошаговая инструкция", "i": "🖥️", "c": "kompyutery-i-noutbuki"}, {"s": "sobrat-kompyuter-za-70000-rublej", "t": "Сборка мощного ПК за 70000 рублей: актуальные комплектующие и конфигурации", "i": "🖥️", "c": "kompyutery-i-noutbuki"}, {"s": "sotovye-stantsii-na-karte", "t": "Сотовые станции на карте: как найти вышки оператора и проверить покрытие", "i": "📶", "c": "set-i-internet"}, {"s": "sotovyj-telefon-iz-90kh", "t": "Сотовый телефон из 90-х: обзор, модели и особенности", "i": "⌚", "c": "elektronika-i-gadzhety"}, {"s": "so-skolki-let-mozhno-sozdat-epl-ajdi", "t": "Ограничения Apple ID: со скольки лет можно создать аккаунт", "i": "🔒", "c": "bezopasnost-i-akkaunty"}, {"s": "sochetanie-klavish-dlya-podcherkivaniya", "t": "Сочетание клавиш для подчеркивания: полные гайды для Windows, Mac и Google Docs", "i": "🖥️", "c": "kompyutery-i-noutbuki"}, {"s": "sony-ericsson-knopochnye-telefony", "t": "Sony Ericsson кнопочные телефоны: обзор, ремонт и покупка", "i": "⌚", "c": "elektronika-i-gadzhety"}, {"s": "sozdanie-lokalnoj-seti-cherez-router", "t": "Настройка локальной сети через Wi-Fi роутер: Полная инструкция", "i": "📶", "c": "set-i-internet"}, {"s": "sochetanie-klavish-dlya-udaleniya-fajla", "t": "Сочетание клавиш для удаления файла: полное руководство по Windows и Mac", "i": "🖥️", "c": "kompyutery-i-noutbuki"}, {"s": "soni-erikson-so-spojlerom", "t": "Сони Эриксон со спойлером: скрытые функции мобильных телефонов", "i": "📱", "c": "smartfony-i-planshety"}, {"s": "sochetanie-klavish-dlya-galochki", "t": "Сочетание клавиш для галочки: Alt+0251 и другие методы", "i": "💿", "c": "soft-i-prilozheniya"}, {"s": "sotovyj-telefon-erikson-90-godov", "t": "Сотовый телефон Ericsson 90-х: раритеты и легенды", "i": "📱", "c": "smartfony-i-planshety"}, {"s": "sochetanie-klavish-uvelichit-masshtab-ekrana", "t": "Сочетание клавиш увеличить масштаб экрана: полный гид по Windows и Mac", "i": "🖥️", "c": "kompyutery-i-noutbuki"}, {"s": "sotovye-telefony-v-90-kh-godakh", "t": "Сотовые телефоны в 90-х: история, модели и цены", "i": "📱", "c": "smartfony-i-planshety"}, {"s": "sozdanie-pary-zanyalo-slishkom-mnogo-vremeni-ubedites-chto-ustrojstvo", "t": "Создание пары заняло много времени: почему висит и как исправить", "i": "📱", "c": "smartfony-i-planshety"}, {"s": "so-skolki-do-skolki-dlitsya-utro-den-vecher-noch", "t": "Во сколько начинается утро, день, вечер и ночь? Точное время", "i": "📁", "c": "drugoe"}, {"s": "sovetskie-plakaty-vremen-vov", "t": "Советские плакаты времен ВОВ: история, художники и символика Великой Победы", "i": "🎮", "c": "igry-i-razvlecheniya"}, {"s": "sochetanie-klavish-dlya-pechati-dokumenta", "t": "Сочетание клавиш для печати: Ctrl+P и скрытые команды", "i": "🖥️", "c": "kompyutery-i-noutbuki"}, {"s": "sokhranenie-na-klaviature-klavishi", "t": "Сохранение на клавиатуре: горячие клавиши и комбинации", "i": "🖥️", "c": "kompyutery-i-noutbuki"}, {"s": "sony-vaio-pcg-5k4p", "t": "Sony VAIO PCG-5K4P: характеристики, ремонт и настройка ноутбука", "i": "🖥️", "c": "kompyutery-i-noutbuki"}, {"s": "sotovyj-telefon-kupit-na-ozon", "t": "Купить сотовый телефон на Ozon: гид по выбору и безопасности", "i": "📱", "c": "smartfony-i-planshety"}, {"s": "sovpadenie-na-chasakh-22-22", "t": "Значение 22:22 на часах: эзотерика, психология и биоритмы", "i": "📁", "c": "drugoe"}, {"s": "sozdat-uchetnuyu-zapis-apple-dlya-rebenka", "t": "Как создать учетную запись Apple для ребенка: пошаговая инструкция", "i": "🔒", "c": "bezopasnost-i-akkaunty"}, {"s": "sobstvennaya-bezopasnost-mvd-eto", "t": "Собственная безопасность МВД: функции, задачи и система защиты", "i": "🔒", "c": "bezopasnost-i-akkaunty"}, {"s": "soprotivlenie-tena-kholodilnika-samsung", "t": "Сопротивление ТЭНа холодильника Самсунг: нормы, проверка, замена", "i": "🔧", "c": "remont-i-diagnostika"}, {"s": "sound-blaster-chto-eto", "t": "Sound Blaster что это: история, технологии и выбор звуковой карты", "i": "🎧", "c": "audio-i-video"}, {"s": "sovpadenie-chisel-13-13", "t": "Совпадение чисел 13 13: Тайны дублирования и нумерология", "i": "📁", "c": "drugoe"}, {"s": "so-skolki-schitaetsya-den-i-do-skolki", "t": "Со скольки считается рабочий день: время начала и конца суток", "i": "📁", "c": null}, {"s": "sochetanie-klavish-dlya-zakrytiya-prilozheniya", "t": "Сочетания клавиш для закрытия приложений: Полный гид по Windows, Mac, Android", "i": "💿", "c": "soft-i-prilozheniya"}, {"s": "sovpadenie-chisel-na-chasakh-22-22", "t": "Значение времени 22:22: Ангельская нумерология и психология совпадений", "i": "📁", "c": "drugoe"}, {"s": "sochetanie-klavish-zakryt-okno", "t": "Сочетание клавиш закрыть окно: полный гид по Alt+F4 и другим", "i": "🖥️", "c": "kompyutery-i-noutbuki"}, {"s": "sovpadayushchie-tsifry-na-chasakh-znachenie", "t": "Значение совпадающих цифр на часах: расшифровка и толкование", "i": "📁", "c": "drugoe"}, {"s": "sochetanie-klavish-sokhranit-kak", "t": "Сочетание клавиш «Сохранить как»: горячие клавиши для Windows и Mac", "i": "💿", "c": "soft-i-prilozheniya"}, {"s": "sotovyj-telefon-pochemu-tak-nazyvaetsya", "t": "Сотовый телефон: почему так называется и как он работает", "i": "⌚", "c": "elektronika-i-gadzhety"}, {"s": "sozdat-eshche-akkaunt-v-vk", "t": "Как создать второй аккаунт ВКонтакте: работающие способы", "i": "🔒", "c": "bezopasnost-i-akkaunty"}, {"s": "sochetanie-klavish-ctrl-w", "t": "Сочетание клавиш Ctrl+W: Полное руководство по использованию в браузере и приложениях", "i": "🖥️", "c": "kompyutery-i-noutbuki"}, {"s": "sochetanie-klavish-dlya-pereimenovaniya", "t": "Сочетание клавиш для переименования файлов в Windows и Mac", "i": "🖥️", "c": "kompyutery-i-noutbuki"}, {"s": "soedinyaet-mnozhestvo-ustrojstv-v-odnu-set", "t": "Как объединить множество устройств в одну сеть: полное руководство", "i": "📶", "c": "set-i-internet"}, {"s": "soni-erikson-krasnyj-knopochnyj", "t": "Sony Ericsson красный кнопочный: обзор редких моделей и ремонт", "i": "⌚", "c": "elektronika-i-gadzhety"}, {"s": "soni-iksperiya-10-plyus", "t": "Sony Xperia 10 Plus: Полный обзор, характеристики и возможности", "i": "📱", "c": "smartfony-i-planshety"}, {"s": "so-skolki-i-do-skolki-nachinaetsya-utro", "t": "Время начала утра: с какого часа оно наступает и когда заканчивается", "i": "📁", "c": "drugoe"}, {"s": "sobiraem-kompyuter-svoimi-rukami-poshagovaya-instruktsiya", "t": "Как собрать компьютер своими руками: Полная пошаговая инструкция", "i": "🖥️", "c": "kompyutery-i-noutbuki"}, {"s": "sochetanie-klavish-nazad-v-brauzere", "t": "Сочетание клавиш «Назад» в браузере: все горячие клавиши навигации", "i": "🖥️", "c": "kompyutery-i-noutbuki"}, {"s": "soobshchenie-ot-0919-prosyat-prislat-obratnoe-sms", "t": "Сообщение от 0919: просят прислать обратное СМС. Что это? | Безопасность", "i": "🔒", "c": "bezopasnost-i-akkaunty"}, {"s": "sotovyj-tarif-bolshe-nedostupen-iphone", "t": "Ошибка «Тариф больше недоступен» на iPhone: причины и способы решения", "i": "📱", "c": "smartfony-i-planshety"}, {"s": "sovetskie-karty-s-polevymi-stanami", "t": "Советские карты с полевыми станами: расшифровка и применение", "i": "📁", "c": "drugoe"}, {"s": "sozdanie-zagruzochnoj-fleshki-mac-os", "t": "Как создать загрузочную флешку macOS: Пошаговая инструкция", "i": "🖥️", "c": "kompyutery-i-noutbuki"}, {"s": "sochetanie-klavish-vyrezat-na-klaviature", "t": "Сочетание клавиш вырезать: Ctrl+X и альтернативы", "i": "🖥️", "c": "kompyutery-i-noutbuki"}, {"s": "sonnet-130-by-william-shakespeare", "t": "Сонет 130 Шекспира: Анализ, смысл и скрытый подтекст", "i": "🎮", "c": "igry-i-razvlecheniya"}, {"s": "sovetskie-voennye-karty-skachat-na-android", "t": "Скачать советские военные карты на Android: полный гайд 2026", "i": "💿", "c": "soft-i-prilozheniya"}, {"s": "sozdat-tochku-dostupa-wifi-na-windows-7", "t": "Как создать точку доступа Wi-Fi на Windows 7: Полная инструкция", "i": "📶", "c": "set-i-internet"}, {"s": "sochetanie-klavish-dlya-pereimenovaniya-fajla", "t": "Сочетание клавиш для переименования файла: F2 и другие горячие клавиши", "i": "🖥️", "c": "kompyutery-i-noutbuki"}, {"s": "sochetanie-klavish-na-klaviature-dlya-kopirovaniya-i-vstavki", "t": "Горячие клавиши копирования и вставки: полный гид по сочетаниям", "i": "🖥️", "c": "kompyutery-i-noutbuki"}, {"s": "soedinitel-filamenta-dlya-3d-printera", "t": "Соединитель филамента для 3D принтера: виды, выбор и использование", "i": "🖨️", "c": "3d-pechat-i-modelirovanie"}, {"s": "sovetskie-voennye-karty-skachat-na-ajfon", "t": "Советские военные карты на iPhone: как скачать и установить", "i": "📱", "c": "smartfony-i-planshety"}, {"s": "sochetanie-klavish-chtoby-vyjti-na-rabochij-stol", "t": "Как быстро выйти на рабочий стол: горячие клавиши Windows", "i": "🖥️", "c": "kompyutery-i-noutbuki"}, {"s": "sochi-edu-ru-proverit-ochered-v-detskij-sad", "t": "Проверить очередь в детский сад Сочи: sochi.edu.ru", "i": "💿", "c": "soft-i-prilozheniya"}, {"s": "sovetskie-voennye-karty-onlajn", "t": "Советские военные карты онлайн: доступ, масштаб, скачивание", "i": "💿", "c": "soft-i-prilozheniya"}, {"s": "solnechnye-chasy-3d-model", "t": "Солнечные часы 3D модель: выбор, настройка и печать", "i": "🖨️", "c": "3d-pechat-i-modelirovanie"}, {"s": "sony-ericsson-starye-modeli", "t": "Коллекция старых моделей Sony Ericsson: история, легендарные кнопочные телефоны и редкие смартфоны", "i": "📱", "c": "smartfony-i-planshety"}, {"s": "sotovye-dannye-tinkoff-mobajl", "t": "Тинькофф Мобайл: тарифы, сотовая связь и управление интернетом", "i": "📶", "c": "set-i-internet"}, {"s": "sovetskie-voennye-karty-apk", "t": "Советские военные карты APK: Обзор приложений для андроида", "i": "💿", "c": "soft-i-prilozheniya"}, {"s": "sovpadenie-vremeni-23-23", "t": "Совпадение времени 23:23: значение и толкование", "i": "📁", "c": "drugoe"}, {"s": "sozdanie-novoj-papki-goryachie-klavishi", "t": "Горячие клавиши для создания папки: Windows и macOS", "i": "🖥️", "c": "kompyutery-i-noutbuki"}, {"s": "sozdatel-alisy-v-strane-chudes", "t": "Создатель Алисы в стране чудес: Льюис Кэрролл и его мир", "i": "📁", "c": "drugoe"}, {"s": "solntse-na-klaviature-simvol", "t": "Как набрать символ солнца ☀️ на клавиатуре: 5 способов для всех ОС", "i": "🖥️", "c": "kompyutery-i-noutbuki"}, {"s": "sonoff-zigbee-bridge-pro-tasmota", "t": "Sonoff Zigbee Bridge Pro с Tasmota: настройка, прошивка и преимущества", "i": "🏠", "c": "umnyj-dom"}, {"s": "soft-dlya-proektirovaniya-mebeli", "t": "Софт для проектирования мебели: выбор, обзор и сравнение", "i": "💿", "c": "soft-i-prilozheniya"}, {"s": "soldatiki-na-3d-printere", "t": "Солдатики на 3D принтере: выбор пластика, настройка и печать фигурок", "i": "🖨️", "c": "3d-pechat-i-modelirovanie"}, {"s": "sovremennyj-brauzer-dlya-windows-xp-32-bit", "t": "Современный браузер для Windows XP 32 bit: актуальный список 2026", "i": "🖥️", "c": "kompyutery-i-noutbuki"}, {"s": "sochetanie-klavish-dlya-serdechka", "t": "Сочетание клавиш для сердечка: Как напечатать символ любви", "i": "💿", "c": "soft-i-prilozheniya"}, {"s": "so-skolki-nachinaetsya-vecher-i-do-skolki", "t": "Во сколько начинается вечер: время суток, законы и световой день", "i": "🏠", "c": "umnyj-dom"}, {"s": "soni-erikson-k-700-god-vypuska", "t": "Sony Ericsson K700: год выпуска, характеристики и история", "i": "📱", "c": "smartfony-i-planshety"}, {"s": "sokhranit-web-stranitsu-v-pdf", "t": "Как сохранить веб-страницу в PDF: Полное руководство 2026", "i": "🖥️", "c": "kompyutery-i-noutbuki"}, {"s": "soocas-zubnaya-shchetka-x3-pro", "t": "Обзор Soocas X3 Pro: характеристики, сравнение и реальная эффективность", "i": "⌚", "c": "elektronika-i-gadzhety"}, {"s": "sostav-promyvochnoj-zhidkosti-dlya-printera-epson", "t": "Состав промывочной жидкости для принтеров Epson: химия и выбор", "i": "🖨️", "c": "printery-i-periferiya"}, {"s": "sovetskie-topograficheskie-karty-skachat", "t": "Советские топографические карты: скачать бесплатно и легально", "i": "💿", "c": "soft-i-prilozheniya"}, {"s": "sovpalo-vremya-na-chasakh", "t": "Совпало время на часах: приметы, значения и психология", "i": "⌚", "c": "elektronika-i-gadzhety"}, {"s": "sobrat-kompyuter-po-komplektuyushchim-samomu-poshagovaya-instruktsiya", "t": "Сборка ПК своими руками: Пошаговая инструкция от выбора до запуска", "i": "🖥️", "c": "kompyutery-i-noutbuki"}, {"s": "sozdanie-domashnej-lokalnoj-seti", "t": "Создание домашней локальной сети: полный гид по настройке", "i": "📶", "c": "set-i-internet"}, {"s": "sobrat-igrovoj-kompyuter-nedorogo-svoimi-rukami", "t": "Как собрать игровой компьютер недорого своими руками: пошаговый гайд", "i": "🖥️", "c": "kompyutery-i-noutbuki"}, {"s": "sochetaniya-klavish-dlya-kopirovaniya", "t": "Сочетания клавиш для копирования: Полное руководство по горячим клавишам", "i": "🖥️", "c": "kompyutery-i-noutbuki"}, {"s": "sobrat-pk-za-40-k", "t": "Сборка ПК за 40 000 рублей: оптимальный конфиг 2026 года", "i": "🖥️", "c": "kompyutery-i-noutbuki"}, {"s": "sochetanie-klavish-chtoby-svernut-vse-okna", "t": "Сочетание клавиш чтобы свернуть все окна: Windows, Mac и Linux", "i": "🖥️", "c": "kompyutery-i-noutbuki"}, {"s": "sochetanie-klavish-dlya-svorachivaniya-vsekh-okon", "t": "Как быстро свернуть все окна: горячие клавиши для Windows и macOS", "i": "🖥️", "c": "kompyutery-i-noutbuki"}, {"s": "soocas-water-flosser-remont", "t": "Ремонт ирригатора Soocas W3: диагностика и устранение поломок", "i": "⌚", "c": "elektronika-i-gadzhety"}, {"s": "sopryazhenie-pulta-s-televizorom-lg", "t": "Как сопрячь пульт с телевизором LG: Полное руководство 2026", "i": "📺", "c": "televizory-i-tv-pristavki"}, {"s": "sopytka-plastik-dlya-3d-printera", "t": "Sopytka пластик для 3D принтера: свойства и настройки", "i": "🖨️", "c": "3d-pechat-i-modelirovanie"}, {"s": "sotovyj-telefon-motorola-s-antennoj", "t": "Сотовый телефон Motorola с антенной: мифы, факты и ностальгия", "i": "📱", "c": "smartfony-i-planshety"}, {"s": "sozdat-marshrut-po-koordinatam", "t": "Создать маршрут по координатам: инструкции для навигаторов и GPS", "i": "💿", "c": "soft-i-prilozheniya"}, {"s": "soni-erikson-pervye-modeli", "t": "Первые модели Sony Ericsson: история, характеристики и легендарные новинки", "i": "⌚", "c": "elektronika-i-gadzhety"}, {"s": "sozdanie-zagruzochnoj-fleshki-win-xp", "t": "Создание загрузочной флешки Windows XP: полное руководство", "i": "🖥️", "c": "kompyutery-i-noutbuki"}, {"s": "sozdat-zagruzochnuyu-fleshku-mac-os", "t": "Как создать загрузочную флешку macOS: Пошаговая инструкция", "i": "🖥️", "c": "kompyutery-i-noutbuki"}, {"s": "soedinitel-dlya-trubok-8-mm", "t": "Соединитель для трубок 8 мм: виды, монтаж и выбор материалов", "i": "🏠", "c": "umnyj-dom"}, {"s": "solnechnaya-panel-dlya-zaryadki-telefona-v-pokhode", "t": "Солнечная панель для зарядки телефона в походе: выбор и советы", "i": "⌚", "c": "elektronika-i-gadzhety"}, {"s": "sonety-shekspira-v-perevode-marshaka-chitat-onlajn-besplatno", "t": "Сонеты Шекспира Маршака: читать онлайн, анализ и особенности перевода", "i": "📁", "c": "drugoe"}, {"s": "sochetanie-klavish-vydelit-vse-fajly-v-papke", "t": "Как быстро выделить все файлы в папке: сочетания клавиш Windows и Mac", "i": "🖥️", "c": "kompyutery-i-noutbuki"}, {"s": "solnechnye-batarei-dlya-zaryadki-telefona", "t": "Солнечные батареи для зарядки телефона: выбор и обзор", "i": "⌚", "c": "elektronika-i-gadzhety"}, {"s": "soni-erikson-chya-firma", "t": "Sony Ericsson чья фирма: история бренда и слияние", "i": "📱", "c": "smartfony-i-planshety"}, {"s": "sochetanie-klavish-alt-f4", "t": "Сочетание клавиш Alt+F4: назначение, функции и альтернативы", "i": "🖥️", "c": "kompyutery-i-noutbuki"}, {"s": "sonoff-wifi-smart-switch-kak-podklyuchit", "t": "Как подключить Sonoff Wi-Fi умный выключатель: Полная инструкция", "i": "🏠", "c": "umnyj-dom"}, {"s": "soobshchenie-ne-mozhet-byt-otpravleno-tak-kak-vremya-ozhidaniya-soedineniya-s-serverom-iskhodyashchej-pochty-smtp", "t": "Ошибка SMTP: как исправить время ожидания соединения с сервером", "i": "💿", "c": "soft-i-prilozheniya"}, {"s": "sobaku-nokhchej-nazovu-akkordy", "t": "Собака Нохчей: Разбор аккордов и музыкальный анализ", "i": "🎧", "c": "audio-i-video"}, {"s": "soni-erikson-vse-modeli-telefonov", "t": "Сони Эриксон: все модели телефонов и история бренда", "i": "📱", "c": "smartfony-i-planshety"}, {"s": "sovremennyj-brauzer-dlya-windows-xp", "t": "Какой браузер установить на Windows XP в 2026: Лучшие варианты и риски", "i": "🖥️", "c": "kompyutery-i-noutbuki"}, {"s": "sozdanie-detskogo-akkaunta-apple", "t": "Создание детского аккаунта Apple ID: пошаговая инструкция для родителей", "i": "🔒", "c": "bezopasnost-i-akkaunty"}, {"s": "soni-erikson-t-610", "t": "Sony Ericsson T610: Легендарный дизайн и особенности модели", "i": "⌚", "c": "elektronika-i-gadzhety"}, {"s": "sozdanie-up-dlya-3d-modeli-v-artcam", "t": "Создание УП для 3D модели в ArtCAM: пошаговая инструкция", "i": "🖨️", "c": "3d-pechat-i-modelirovanie"}, {"s": "sozdat-akkaunt-xiaomi-po-nomeru-telefona", "t": "Как создать аккаунт Xiaomi по номеру телефона: полная инструкция", "i": "📱", "c": "smartfony-i-planshety"}, {"s": "sovpadenie-chisel-na-chasakh-12-12", "t": "Значение 12:12 на часах: мистика, психология и нумерология", "i": "📁", "c": "drugoe"}, {"s": "sozdat-kitajskij-nomer-telefona", "t": "Как создать китайский номер телефона: способы получения и активации", "i": "📶", "c": "set-i-internet"}, {"s": "sozdat-nik-iz-simvolov", "t": "Как создать ник из символов: генераторы, шрифты и символы", "i": "💿", "c": "soft-i-prilozheniya"}, {"s": "sobiraem-igrovoj-kompyuter-nedorogoj-no-moshchnyj", "t": "Сборка недорогого, но мощного игрового ПК: полный гид 2026", "i": "🖥️", "c": "kompyutery-i-noutbuki"}, {"s": "sochetanie-klavish-dlya-vtorogo-rabochego-stola", "t": "Горячие клавиши для второго рабочего стола в Windows: Полная инструкция", "i": "🖥️", "c": "kompyutery-i-noutbuki"}, {"s": "sochetanie-klavish-dlya-vydeleniya", "t": "Сочетание клавиш для выделения текста и файлов: полный гид", "i": "🖥️", "c": "kompyutery-i-noutbuki"}, {"s": "sobesednik-slyshit-sebya-pri-razgovore-v-telefone", "t": "Собеседник слышит себя: причины эха в телефоне и способы устранения", "i": "📱", "c": "smartfony-i-planshety"}, {"s": "sochetaniya-klavish-chtoby-svernut-vse-okna", "t": "Как свернуть все окна: сочетания клавиш Win+D и другие способы", "i": "🖥️", "c": "kompyutery-i-noutbuki"}, {"s": "sokhranit-video-iz-dzena", "t": "Как скачать видео из Дзен: 5 проверенных способов", "i": "💿", "c": "soft-i-prilozheniya"}, {"s": "soplo-dlya-3d-printera-ender-3", "t": "Сопло для Ender 3: выбор, установка и лучшие материалы", "i": "🖨️", "c": "3d-pechat-i-modelirovanie"}, {"s": "sound-blaster-acoustic-engine", "t": "Sound Blaster Acoustic Engine: настройка и функции | Полный гайд", "i": "🎧", "c": "audio-i-video"}, {"s": "sochetanie-klavish-dlya-zakrytiya-vsekh-okon", "t": "Сочетание клавиш для закрытия всех окон: Полное руководство", "i": "🖥️", "c": "kompyutery-i-noutbuki"}, {"s": "sonoff-basic-r2-kak-podklyuchit", "t": "Sonoff Basic R2: схема подключения и настройка WiFi", "i": "🏠", "c": "umnyj-dom"}, {"s": "sozdanie-marshruta-na-karte-s-neskolkimi-tochkami", "t": "Как создать маршрут на карте с несколькими точками: Пошаговая инструкция", "i": "💿", "c": "soft-i-prilozheniya"}, {"s": "soft-dlya-3d-modelirovaniya-dlya-3d-printera", "t": "Лучший софт для 3D моделирования: выбираем программы для печати", "i": "🖨️", "c": "3d-pechat-i-modelirovanie"}, {"s": "soneta-130-shekspira-na-anglijskom", "t": "Сонет 130 Шекспира: оригинал на английском, перевод и разбор", "i": "📁", "c": "drugoe"}, {"s": "sozdat-akkaunt-v-kinopoiske", "t": "Создать аккаунт в Кинопоиске: пошаговая инструкция 2026", "i": "💿", "c": "soft-i-prilozheniya"}, {"s": "sozdat-rington-cherez-garazh-bend", "t": "Как создать рингтон через GarageBand: пошаговая инструкция", "i": "📱", "c": "smartfony-i-planshety"}, {"s": "so-skolki-do-skolki-dlitsya-utro", "t": "Со скольки до скольки длится утро: Нормы времени и биоритмы", "i": "📁", "c": "drugoe"}, {"s": "sobesednik-ne-slyshit-menya-cherez-naushniki", "t": "Собеседник не слышит меня в наушниках: причины и способы решения", "i": "🎧", "c": "audio-i-video"}, {"s": "sozdanie-zagruzhaemogo-ustanovshchika-dlya-macos", "t": "Создание загрузочного USB для macOS: полная инструкция", "i": "🖥️", "c": "kompyutery-i-noutbuki"}, {"s": "sochetanie-klavish-chtoby-zakryt-vse-okna", "t": "Сочетания клавиш для закрытия всех окон: Полный гайд для Windows, macOS и Linux", "i": "🖥️", "c": "kompyutery-i-noutbuki"}, {"s": "sotrudnik-politsii-zabiraet-kompyuter", "t": "Сотрудник полиции забирает компьютер: права и действия", "i": "🔒", "c": "bezopasnost-i-akkaunty"}, {"s": "software-wow-and-flutter-meter", "t": "Software Wow and Flutter Meter: Точность измерения аудиоискажений", "i": "🎧", "c": "audio-i-video"}, {"s": "soprotivlenie-datchika-temperatury-kholodilnika-samsung", "t": "Сопротивление датчика температуры холодильника Samsung: таблица и диагностика", "i": "🔧", "c": "remont-i-diagnostika"}, {"s": "sovpadenie-tsifr-na-chasakh-chto-oznachaet", "t": "Совпадение цифр на часах: значение и толкование", "i": "📁", "c": "drugoe"}, {"s": "sochetanie-klavish-chtoby-zakryt-vse-vkladki", "t": "Сочетание клавиш чтобы закрыть все вкладки: Полное руководство", "i": "💿", "c": "soft-i-prilozheniya"}, {"s": "sochetanie-klavish-novaya-papka", "t": "Сочетание клавиш новая папка: Hotkey для Windows и Mac", "i": "🖥️", "c": "kompyutery-i-noutbuki"}, {"s": "sochetaniya-simvolov-dlya-oformleniya", "t": "Символы для оформления текста: таблицы, списки и редкие знаки", "i": "💿", "c": "soft-i-prilozheniya"}, {"s": "soobshcheniya-na-telefone-ne-otkryvayutsya", "t": "Сообщения не открываются на телефоне: причины и решение", "i": "📱", "c": "smartfony-i-planshety"}, {"s": "sovetskij-razem-dlya-naushnikov", "t": "Советский разъем для наушников: виды, распиновка и схемы", "i": "🎧", "c": "audio-i-video"}, {"s": "sonoff-ne-podklyuchaetsya-k-wifi", "t": "Sonoff не подключается к WiFi: причины, методы сброса и решения", "i": "🏠", "c": "umnyj-dom"}, {"s": "sovetskie-voennye-karty-pro-4pda", "t": "Советские военные карты на 4PDA: Где скачать и как использовать", "i": "💿", "c": "soft-i-prilozheniya"}, {"s": "sozdat-drugoj-akkaunt-v-vk", "t": "Как создать второй аккаунт в ВК: полная инструкция 2026", "i": "🔒", "c": "bezopasnost-i-akkaunty"}, {"s": "solidworks-simulation-kak-vklyuchit", "t": "Как включить SolidWorks Simulation: Пошаговая настройка и активация", "i": "💿", "c": "soft-i-prilozheniya"}, {"s": "sony-xperia-z1-razborka", "t": "Sony Xperia Z1 разборка: пошаговая инструкция, фото, инструменты", "i": "🔧", "c": "remont-i-diagnostika"}, {"s": "sovetskie-voennye-karty-na-ajfon", "t": "Советские военные карты на iPhone: приложения, форматы и установка", "i": "📱", "c": "smartfony-i-planshety"}, {"s": "sovpadenie-chisel-na-chasakh-znachenie-kombinatsij", "t": "Совпадение чисел на часах: значение комбинаций и расшифровка", "i": "📁", "c": "drugoe"}, {"s": "sochetanie-klavish-dlya-pechati", "t": "Сочетание клавиш для печати: горячие кнопки принтера и сканирования", "i": "🖨️", "c": "printery-i-periferiya"}, {"s": "sony-vaio-vgn-p11z", "t": "Sony VAIO VGN-P11Z: характеристики, ремонт и апгрейд", "i": "🖥️", "c": "kompyutery-i-noutbuki"}, {"s": "soobshcheniya-ot-moshennikov-tekst", "t": "Сообщения от мошенников: текст, примеры и способы защиты", "i": "🔒", "c": "bezopasnost-i-akkaunty"}, {"s": "sotovyj-telefon-s-antennoj", "t": "Сотовый телефон с антенной: выбор, настройка и усиление сигнала", "i": "⌚", "c": "elektronika-i-gadzhety"}, {"s": "sozdat-akkaunt-na-huawei", "t": "Как создать аккаунт Huawei ID: пошаговая инструкция 2026", "i": "🔒", "c": "bezopasnost-i-akkaunty"}, {"s": "sochetanie-klavish-chtoby-najti-slovo-v-tekste", "t": "Сочетание клавиш чтобы найти слово в тексте: полный гид", "i": "💿", "c": "soft-i-prilozheniya"}, {"s": "sochetanie-klavish-vin-r", "t": "Win + R: Полный гайд по горячим клавишам Windows для скорости", "i": "🖥️", "c": "kompyutery-i-noutbuki"}, {"s": "soni-erikson-telefony-vse-modeli", "t": "Сони Эриксон: все модели телефонов, линейки и легендарные серии", "i": "📱", "c": "smartfony-i-planshety"}, {"s": "soobshcheniya-v-telegramme-prikhodyat-tolko-kogda-zakhodish-v-prilozhenie", "t": "Сообщения в Telegram приходят только при входе: причины и исправление", "i": "📱", "c": "smartfony-i-planshety"}, {"s": "soobshcheniya-vatsap-prikhodyat-tolko-pri-otkrytii-prilozheniya", "t": "Сообщения WhatsApp приходят только при открытии: решаем проблему", "i": "📱", "c": "smartfony-i-planshety"}, {"s": "sozdanie-3-d-modeli-dlya-3-d-printera", "t": "Создание 3D модели для 3D принтера: полное руководство", "i": "🖨️", "c": "3d-pechat-i-modelirovanie"}, {"s": "sozdat-mi-account-dlya-xiaomi", "t": "Как создать Mi Account для Xiaomi: пошаговая регистрация и вход", "i": "📱", "c": "smartfony-i-planshety"}, {"s": "sobachka-simvol-na-klaviature", "t": "Символ собаки @ на клавиатуре: как найти и ввести в разных ОС", "i": "🖥️", "c": "kompyutery-i-noutbuki"}, {"s": "sochetanie-klavish-dlya-razvorota-okna-na-ves-ekran", "t": "Сочетание клавиш для разворота окна: все горячие клавиши", "i": "🖥️", "c": "kompyutery-i-noutbuki"}, {"s": "sozdat-epl-ajdi-dlya-rebenka-do-13-let", "t": "Как создать Apple ID для ребенка до 13 лет: Инструкция", "i": "🔒", "c": "bezopasnost-i-akkaunty"}, {"s": "sonoff-zigbee-dongle-e-proshivka", "t": "Прошивка Sonoff Zigbee Dongle E: инструкция, версии и ошибки", "i": "🏠", "c": "umnyj-dom"}, {"s": "sovetskie-voennye-topograficheskie-karty", "t": "Советские военные топографические карты: масштаб, обозначения и где найти", "i": "📁", "c": "drugoe"}, {"s": "sobrat-pk-za-40k-igrovoj", "t": "Собрать игровой ПК за 40000 руб: пошаговая сборка 2026", "i": "🖥️", "c": "kompyutery-i-noutbuki"}, {"s": "soft-dlya-3d-printera", "t": "Софт для 3D принтера: выбор, настройка и слайсеры", "i": "🖨️", "c": "3d-pechat-i-modelirovanie"}, {"s": "sovet-300-mirovoe-pravitelstvo", "t": "Совет 300: Мировое правительство или выдумка?", "i": "📁", "c": "drugoe"}, {"s": "sovpadenie-chisel-na-chasakh-13-13", "t": "13:13 на часах: мистика, психология и суеверия", "i": "📁", "c": "drugoe"}, {"s": "sozdat-akkaunt-apple-na-iphone", "t": "Как создать аккаунт Apple ID на iPhone: полная инструкция 2026", "i": "📱", "c": "smartfony-i-planshety"}, {"s": "sozdat-papku-v-vindovs-goryachie-klavishi", "t": "Горячие клавиши для создания папки в Windows: все способы", "i": "🖥️", "c": "kompyutery-i-noutbuki"}, {"s": "sokrovishcha-valkirii-alekseev-otzyvy", "t": "Сокровища Валькирии Алексеев: отзывы, особенности и вердикт", "i": "🎮", "c": "igry-i-razvlecheniya"}, {"s": "so-skolki-do-skolki-dlitsya-utro-den-vecher", "t": "Во сколько начинается утро, день, вечер и ночь: ГОСТ и биоритмы", "i": "🏠", "c": "umnyj-dom"}, {"s": "so-skolki-let-mozhno-sozdat-ajklaud", "t": "Со скольки лет можно создать iCloud: правила и ограничения", "i": "📱", "c": "smartfony-i-planshety"}, {"s": "sovpadenie-chisel-21-21", "t": "Ангельское число 21: Значение, толкование и совпадения", "i": "📁", "c": "drugoe"}, {"s": "sochetanie-klavish-windows-r", "t": "Комбинация клавиш Windows + R: полная инструкция и список команд Run", "i": "💿", "c": "soft-i-prilozheniya"}, {"s": "sozdat-novuyu-papku-goryachie-klavishi-windows-10", "t": "Как создать новую папку в Windows 10 горячими клавишами", "i": "🖥️", "c": "kompyutery-i-noutbuki"}, {"s": "sozdat-novyj-akkaunt-v-vk-na-odin-nomer", "t": "Как создать новый аккаунт в ВК на один номер телефона?", "i": "🔒", "c": "bezopasnost-i-akkaunty"}, {"s": "sozdat-ustanovochnuyu-fleshku-mac-os", "t": "Как создать загрузочную флешку macOS: Пошаговая инструкция 2026", "i": "🖥️", "c": "kompyutery-i-noutbuki"}, {"s": "so-skolkikh-chasov-nachinaetsya-den", "t": "Со скольких часов начинается день: официальное время и биоритмы", "i": "💿", "c": "soft-i-prilozheniya"}, {"s": "sopli-pri-3d-pechati-petg", "t": "Сопли при 3D печати PETG: причины и устранение", "i": "🖨️", "c": "3d-pechat-i-modelirovanie"}, {"s": "sozdatel-microsoft-4-bukvy", "t": "Кто создал Microsoft: 4 буквы и история успеха Билла Гейтса", "i": "💿", "c": "soft-i-prilozheniya"}, {"s": "so-skolki-i-do-skolki-schitaetsya-utro", "t": "Во сколько начинается и заканчивается утро: определение времени", "i": "🏠", "c": "umnyj-dom"}, {"s": "sochetanie-klavish-sozdat-novuyu-papku", "t": "Сочетание клавиш создать новую папку: Windows, macOS и Android", "i": "🖥️", "c": "kompyutery-i-noutbuki"}, {"s": "sotovye-vyshki-lokator-4pda", "t": "Сотовые вышки локатор 4pda: поиск базовых станций", "i": "📱", "c": "smartfony-i-planshety"}, {"s": "sovpadenie-na-chasakh-11-11", "t": "Совпадение 11:11: мистическое значение, психология и как правильно загадать желание", "i": "📁", "c": "drugoe"}, {"s": "sony-naushniki-besprovodnye-kak-podklyuchitsya", "t": "Как подключить наушники Sony Bluetooth: полная инструкция", "i": "🎧", "c": "audio-i-video"}, {"s": "sound-blaster-g6-nastrojka", "t": "Настройка Sound Blaster G6: полный гид по драйверам и звуку", "i": "🎧", "c": "audio-i-video"}, {"s": "sozdat-zagruzochnuyu-fleshku-high-sierra", "t": "Как создать загрузочную флешку macOS High Sierra: Пошаговая инструкция", "i": "💿", "c": "soft-i-prilozheniya"}, {"s": "so-skolki-chasov-nachinaetsya-vecher-i-do-skolki", "t": "Со скольки часов начинается вечер: время суток по правилам", "i": "📁", "c": "drugoe"}, {"s": "sotovye-dannye-nedostupny-vo-vremya-vyzova", "t": "Сотовые данные недоступны во время вызова: причины и решения", "i": "📱", "c": "smartfony-i-planshety"}, {"s": "sovmestimost-ddr3-i-ddr3l", "t": "Совместимость DDR3 и DDR3L: отличия, напряжение и риски", "i": "🖥️", "c": "kompyutery-i-noutbuki"}, {"s": "sovpadenie-chisel-na-chasakh-14-14", "t": "Значение чисел 14:14 на часах: эзотерика, нумерология и психология", "i": "📁", "c": "drugoe"}, {"s": "sochetanie-klavish-dlya-vyrezat", "t": "Сочетание клавиш для вырезать: Горячие клавиши в Windows, Mac и Linux", "i": "🖥️", "c": "kompyutery-i-noutbuki"}, {"s": "soedinit-router-s-routerom-po-kabelyu", "t": "Как соединить два роутера по кабелю: пошаговая настройка", "i": "📶", "c": "set-i-internet"}, {"s": "soni-erikson-telefon-knopochnyj-vse-modeli", "t": "Все модели кнопочных телефонов Sony Ericsson: Обзор и характеристики", "i": "⌚", "c": "elektronika-i-gadzhety"}, {"s": "sound-bar-xiaomi-mi", "t": "Sound Bar Xiaomi Mi: Обзор, настройка и выбор моделей", "i": "🎧", "c": "audio-i-video"}, {"s": "sozdat-tochku-dostupa-wifi-windows-11", "t": "Как создать точку доступа Wi-Fi в Windows 11: Полная инструкция", "i": "📶", "c": "set-i-internet"}, {"s": "sozdat-ustanovochnuyu-fleshku-windows-xp", "t": "Как создать установочную флешку Windows XP: полная инструкция", "i": "🖥️", "c": "kompyutery-i-noutbuki"}, {"s": "sochetanie-klavish-dlya-izmeneniya-registra", "t": "Сочетания клавиш для смены регистра: полный гид для Windows и Mac", "i": "💿", "c": "soft-i-prilozheniya"}, {"s": "sochetanie-klavish-dlya-kopirovaniya-i-vstavki-teksta", "t": "Сочетание клавиш для копирования и вставки: полный гид по горячим клавишам", "i": "🖥️", "c": "kompyutery-i-noutbuki"}, {"s": "sochetanie-klavish-dlya-provodnika", "t": "Горячие клавиши для Проводника Windows: полный список сочетаний", "i": "💿", "c": "soft-i-prilozheniya"}, {"s": "sokhranit-klavishi-na-klaviature-kompyutera", "t": "Как сохранить раскладку и настройки клавиатуры: полное руководство", "i": "🖥️", "c": "kompyutery-i-noutbuki"}, {"s": "sony-ericsson-pervye-modeli", "t": "Первые модели Sony Ericsson: история, характеристики и обзор", "i": "📱", "c": "smartfony-i-planshety"}, {"s": "sobrat-komp-za-60k", "t": "Сборка игрового ПК за 60 000 рублей: лучший конфиг 2026 года", "i": "🖥️", "c": "kompyutery-i-noutbuki"}, {"s": "solntse-v-tekste-simvol", "t": "Символ солнца в тексте: значение, кодировка и использование", "i": "💿", "c": "soft-i-prilozheniya"}, {"s": "soni-erikson-s-tonkimi-knopkami", "t": "Sony Ericsson с тонкими кнопками: обзор и ремонт", "i": "📱", "c": "smartfony-i-planshety"}, {"s": "sound-blaster-control-panel-skachat", "t": "Sound Blaster Control Panel: скачать драйвер и настроить звук", "i": "🎧", "c": "audio-i-video"}, {"s": "so-skolki-i-do-skolki-idet-noch", "t": "Со скольки и до скольки идет ночь: понятие и границы", "i": "📁", "c": "drugoe"}, {"s": "sobrat-3d-printer-svoimi-rukami", "t": "Как собрать 3D принтер своими руками: полное руководство", "i": "🖨️", "c": "3d-pechat-i-modelirovanie"}, {"s": "sobrat-igrovoj-pk-za-100k", "t": "Собрать игровой ПК за 100 000 рублей: Идеальная сборка 2026", "i": "🖥️", "c": "kompyutery-i-noutbuki"}, {"s": "sochetanie-klavish-chtoby-sozdat-papku", "t": "Сочетание клавиш для создания папки: Windows и Mac", "i": "🖥️", "c": "kompyutery-i-noutbuki"}, {"s": "soldatiki-dlya-3d-printera", "t": "Солдатики для 3д принтера: материалы, модели и печать фигурок", "i": "🖨️", "c": "3d-pechat-i-modelirovanie"}, {"s": "sochetanie-knopok-na-klaviature-kompyutera", "t": "Сочетание кнопок на клавиатуре: Полный список горячих клавиш", "i": "🖥️", "c": "kompyutery-i-noutbuki"}, {"s": "soldatiki-3d-model-dlya-pechati", "t": "3D модели солдатиков для печати: где скачать и как печатать", "i": "🖨️", "c": "3d-pechat-i-modelirovanie"}, {"s": "sopli-pri-pechati-petg", "t": "Сопли при печати PETG: причины, настройка и полное решение", "i": "🖨️", "c": "3d-pechat-i-modelirovanie"}, {"s": "sound-blaster-ae-5", "t": "Sound Blaster AE-5: Обзор, Установка и Настройка Звука в ПК", "i": "🎧", "c": "audio-i-video"}, {"s": "sovpadenie-chisel-na-chasakh-1212", "t": "1212 на часах: значение, нумерология и психология совпадений", "i": "📁", "c": "drugoe"}, {"s": "sozdat-3d-model-zdaniya", "t": "Как создать 3д модель здания: пошаговый гайд и выбор софта", "i": "🖨️", "c": "3d-pechat-i-modelirovanie"}, {"s": "so-skolki-vremeni-schitaetsya-noch", "t": "Со скольки часов считается ночь в России и мире", "i": "📁", "c": null}, {"s": "sochetanie-klavish-win-r-na-klaviature", "t": "Сочетание клавиш Win+R: полный справочник команд и трюков", "i": "🖥️", "c": "kompyutery-i-noutbuki"}, {"s": "soedinenie-routerov-lan-wan", "t": "Как соединить роутеры через LAN и WAN: Полное руководство по настройке", "i": "📶", "c": "set-i-internet"}, {"s": "so-skolko-chasov-nachinaetsya-vecher", "t": "Со скольки часов начинается вечер: время по закону и биоритмам", "i": "📁", "c": null}, {"s": "soobshchit-o-moshennikakh-megafon", "t": "Как сообщить о мошенниках Мегافон: куда звонить и писать жалобу", "i": "🔒", "c": "bezopasnost-i-akkaunty"}, {"s": "sozdat-akkaunt-epl-stor", "t": "Как создать аккаунт Apple ID для App Store: полная инструкция", "i": "🔒", "c": "bezopasnost-i-akkaunty"}, {"s": "solnechnaya-batareya-na-telefon", "t": "Солнечная батарея на телефон: виды, эффективность и выбор зарядки", "i": "📱", "c": "smartfony-i-planshety"}, {"s": "sotovyj-tarif-udalen-iphone", "t": "Сотовый тариф удален на iPhone: причины и решение", "i": "📱", "c": "smartfony-i-planshety"}, {"s": "sozvonilas-ili-sozvanilas-kak-pravilno", "t": "Созвонилась или созванилась: как правильно и почему", "i": "📁", "c": "drugoe"}, {"s": "sochetanie-klavish-dlya-otkrytiya-poslednej-zakrytoj-vkladki", "t": "Как открыть последнюю закрытую вкладку: сочетания клавиш для всех браузеров", "i": "💿", "c": "soft-i-prilozheniya"}, {"s": "so-skolki-do-skolki-chasov-den", "t": "Сколько длится день: от рассвета до заката и границы суток", "i": "📶", "c": "set-i-internet"}, {"s": "so-skolki-vremeni-nachinaetsya-vecher", "t": "Со скольки начинается вечер: точное время по нормам и астрономии", "i": "📁", "c": "drugoe"}, {"s": "sochetanie-klavish-na-klaviature-dlya-pechati", "t": "Горячие клавиши для печати: как печатать быстрее и эффективнее", "i": "🖥️", "c": "kompyutery-i-noutbuki"}, {"s": "sony-ericsson-modeli-po-godam", "t": "История телефонов Sony Ericsson: все модели по годам выпуска", "i": "📱", "c": "smartfony-i-planshety"}, {"s": "sozdat-akkaunt-khuavej-dlya-telefona", "t": "Как создать аккаунт Huawei для телефона: полная инструкция 2026", "i": "📱", "c": "smartfony-i-planshety"}, {"s": "sochetanie-klavish-bufer-obmena", "t": "Сочетания клавиш буфера обмена: полное руководство для Windows и Mac", "i": "🖥️", "c": "kompyutery-i-noutbuki"}, {"s": "sochetanie-klavish-udalit-bezvozvratno", "t": "Сочетание клавиш удалить безвозвратно файлы в Windows", "i": "🖥️", "c": "kompyutery-i-noutbuki"}, {"s": "son-mne-v-ruku-vysotskij", "t": "Сон мне в руку Высотецкий: значение фразы и анализ текста", "i": "🎮", "c": "igry-i-razvlecheniya"}, {"s": "sopli-pri-pechati-pla", "t": "Сопли при печати PLA: причины, лечение и настройка экструдера", "i": "🖨️", "c": "3d-pechat-i-modelirovanie"}, {"s": "soni-erikson-s-dzhojstikom-staryj", "t": "Сони Эриксон с джойстиком: обзор легендарных моделей и сохранение", "i": "⌚", "c": "elektronika-i-gadzhety"}, {"s": "soobshchit-o-moshennichestve-megafon", "t": "Как сообщить о мошенничестве МегаФон: инструкция и контакты", "i": "🔒", "c": "bezopasnost-i-akkaunty"}, {"s": "sotrudnichestvo-s-valberis-gruzoperevozki-na-svoem-avto", "t": "Сотрудничество с Wildberries: грузоперевозки на своем авто", "i": "📁", "c": "drugoe"}, {"s": "sovetskie-karty-pro-na-android-skachat", "t": "Советские карты для Android: как скачать и настроить", "i": "📱", "c": "smartfony-i-planshety"}, {"s": "sovpadenie-chisel-22-22-na-chasakh-znachenie", "t": "Совпадение чисел 22:22 на часах: значение и толкование", "i": "⌚", "c": "elektronika-i-gadzhety"}, {"s": "sobesednik-menya-ne-slyshit-po-telefonu-chto-delat", "t": "Собеседник не слышит вас: что делать, если пропал микрофон", "i": "📱", "c": "smartfony-i-planshety"}, {"s": "sobrat-umnyj-dom-s-alisoj", "t": "Как собрать умный дом с Алисой: полное руководство по настройке", "i": "🏠", "c": "umnyj-dom"}, {"s": "sochetanie-tsifr-na-chasakh-znachenie", "t": "Сочетание цифр на часах: значение, эзотерика и психология синхроничности", "i": "📁", "c": "drugoe"}, {"s": "sochetanie-klavish-dlya-okonnogo-rezhima", "t": "Сочетание клавиш для оконного режима: полный гид по Alt+Enter и не только", "i": "🖥️", "c": "kompyutery-i-noutbuki"}, {"s": "sochetanie-klavish-shag-vpered", "t": "Сочетание клавиш «Шаг вперед»: управление в Windows, Word и Браузерах", "i": "🖥️", "c": "kompyutery-i-noutbuki"}, {"s": "sozdat-2-akkaunt-v-vk", "t": "Как создать второй аккаунт ВКонтакте: безопасные способы и советы", "i": "🔒", "c": "bezopasnost-i-akkaunty"}, {"s": "sozdat-papku-goryachie-klavishi-windows-11", "t": "Создать папку: горячие клавиши Windows 11. Полный гид", "i": "🖥️", "c": "kompyutery-i-noutbuki"}, {"s": "sochetanie-goryachikh-klavish-na-klaviature", "t": "Сочетания горячих клавиш: полный гид по повышению эффективности", "i": "🖥️", "c": "kompyutery-i-noutbuki"}, {"s": "solomon-ya-prevzoshel-tebya", "t": "Соломон я превзошел тебя: разбор фразы и её происхождения", "i": "📁", "c": "drugoe"}, {"s": "sony-vaio-mini-noutbuk", "t": "Sony VAIO мини-ноутбук: Обзор легендарных моделей и советы по выбору", "i": "🖥️", "c": "kompyutery-i-noutbuki"}, {"s": "sound-blaster-g6-programma", "t": "Sound Blaster G6: программа, драйверы и настройка", "i": "🎧", "c": "audio-i-video"}, {"s": "soedinitel-niti-dlya-3d-printera", "t": "Соединитель нити для 3D принтера: виды, выбор и методы склейки", "i": "🖨️", "c": "3d-pechat-i-modelirovanie"}, {"s": "sozdat-mi-akkaunt-na-xiaomi", "t": "Как создать Mi аккаунт Xiaomi: инструкция по регистрации", "i": "📱", "c": "smartfony-i-planshety"}, {"s": "sobesednik-slyshit-sam-sebya-v-telefone", "t": "Эхо в трубке: почему собеседник слышит сам себя при звонке", "i": "📱", "c": "smartfony-i-planshety"}, {"s": "sochetanie-klavish-chtoby-pereimenovat-fajl", "t": "Сочетание клавиш для переименования файла: F2, Alt+Enter и другие", "i": "🖥️", "c": "kompyutery-i-noutbuki"}, {"s": "sochetanie-klavish-dlya-kopirovaniya", "t": "Комбинации клавиш для копирования: Полный гайд по Ctrl+C, Cmd+C и альтернативам", "i": "🖥️", "c": "kompyutery-i-noutbuki"}, {"s": "sochetanie-klavish-dlya-poiska-po-tekstu", "t": "Горячие клавиши для поиска по тексту: полный гайд", "i": "💿", "c": "soft-i-prilozheniya"}, {"s": "soni-erikson-k-320", "t": "Sony Ericsson K320: Обзор легендарного телефона и особенности ремонта", "i": "📱", "c": "smartfony-i-planshety"}, {"s": "soobshchenie-chto-mozhno-napechatat-na-3d-printere", "t": "Что можно напечатать на 3D принтере: идеи, модели и утилиты", "i": "🖨️", "c": "3d-pechat-i-modelirovanie"}, {"s": "sonoff-zb-dongle-e", "t": "Sonoff ZB Dongle E: Подробный обзор и настройка Z-иглы", "i": "🏠", "c": "umnyj-dom"}, {"s": "sound-blaster-ae5-plus", "t": "Creative Sound Blaster AE-5 Plus: Обзор и Настройка", "i": "🎧", "c": "audio-i-video"}, {"s": "sozdanie-3-d-modelej-dlya-printera", "t": "Создание 3D моделей для 3D принтера: полное руководство", "i": "🖨️", "c": "3d-pechat-i-modelirovanie"}, {"s": "solist-rok-gruppy-alisa", "t": "Солист рок-группы Алиса: Константин Кинчев и история легенды", "i": "🎧", "c": "audio-i-video"}, {"s": "soobshchenie-o-perevode-deneg-sberbank", "t": "Как написать сообщение о переводе денег в СберБанк Онлайн", "i": "🔒", "c": "bezopasnost-i-akkaunty"}, {"s": "sochetanie-klavish-vernut-vpered", "t": "Сочетание клавиш 'Вернуть вперед': Полный гайд по горячим клавишам", "i": "🖥️", "c": "kompyutery-i-noutbuki"}, {"s": "sopla-kartridzha-kak-pochistit", "t": "Как почистить сопла картриджа: 5 проверенных методов", "i": "🖨️", "c": "printery-i-periferiya"}, {"s": "sound-blaster-ae-7", "t": "Creative Sound Blaster AE-7: Обзор, настройки и разбор характеристик", "i": "🎧", "c": "audio-i-video"}, {"s": "so-vremenem-padaet-skorost-interneta", "t": "Почему падает скорость интернета со временем: причины и решение", "i": "📶", "c": "set-i-internet"}, {"s": "sony-xperia-xz1-compact-4pda", "t": "Sony Xperia XZ1 Compact: характеристики и форум 4PDA", "i": "📱", "c": "smartfony-i-planshety"}, {"s": "sovetskie-kompyutery-80-kh", "t": "Советские компьютеры 80-х: обзор, модели и история", "i": "🖥️", "c": "kompyutery-i-noutbuki"}, {"s": "sochetaniya-klavish-dlya-pechati", "t": "Сочетания клавиш для печати: горячие клавиши Ctrl+P и не только", "i": "🖥️", "c": "kompyutery-i-noutbuki"}, {"s": "sozdanie-tochki-dostupa-na-telefone-android", "t": "Точка доступа на Android: настройка и устранение проблем", "i": "📱", "c": "smartfony-i-planshety"}, {"s": "sozdat-detskij-apple-id", "t": "Как создать детский Apple ID: пошаговая инструкция для родителей", "i": "🔒", "c": "bezopasnost-i-akkaunty"}, {"s": "sobiraem-pk-s-nulya", "t": "Как собрать ПК с нуля: пошаговая инструкция, выбор комплектующих и сборка", "i": "🖥️", "c": "kompyutery-i-noutbuki"}, {"s": "soplo-ne-nagrevaetsya-kak-ozhidalos-creality-k1", "t": "Creality K1: сопло не нагревается — причины и ремонт", "i": "🖨️", "c": "3d-pechat-i-modelirovanie"}, {"s": "sos-kak-podat-signal-stukom", "t": "Как подать сигнал стуком: руководство по SOS в чрезвычайных ситуациях", "i": "🔒", "c": "bezopasnost-i-akkaunty"}, {"s": "so-skolki-schitaetsya-vecher", "t": "Со скольки часов считается вечер: нормы, биоритмы и правила", "i": "🏠", "c": "umnyj-dom"}, {"s": "soni-erikson-modelnyj-ryad", "t": "История и модельный ряд Sony Ericsson: от кнопок до смартфонов", "i": "📱", "c": "smartfony-i-planshety"}, {"s": "sotvorenie-mira-spektakl-obraztsova", "t": "Спектакль «Сотворение мира» в Театре Образцова: сюжет, отзывы и как купить билет", "i": "🎮", "c": "igry-i-razvlecheniya"}, {"s": "sokhranit-dokument-klavishi-na-klaviature", "t": "Горячие клавиши для сохранения документа: Ctrl+S и альтернативы", "i": "💿", "c": "soft-i-prilozheniya"}, {"s": "solnechnaya-panel-dlya-zaryadki-poverbanka", "t": "Солнечная панель для повербанка: выбор, эффективность и нюансы зарядки", "i": "⌚", "c": "elektronika-i-gadzhety"}, {"s": "sovremennyj-sistemnyj-blok-dlya-kompyutera", "t": "Сборка современного системного блока: выбор компонентов и советы 2026", "i": "🖥️", "c": "kompyutery-i-noutbuki"}, {"s": "sozdat-simvol-i-skopirovat", "t": "Создать символ и скопировать: спецзнаки, эмодзи и символы для текста", "i": "💿", "c": "soft-i-prilozheniya"}, {"s": "sozdat-tandem-s-yandeks-stantsiej", "t": "Как создать тандем с Яндекс Станцией: настройка мультирума и дуэта", "i": "🏠", "c": "umnyj-dom"}, {"s": "sozdat-zagruzochnuyu-fleshku-windows-10-uefi", "t": "Создать загрузочную флешку Windows 10 UEFI: Полная инструкция 2026", "i": "🖥️", "c": "kompyutery-i-noutbuki"}, {"s": "sotovyj-telefon-motorola-2000-godov", "t": "Моторола 2000-х: Легенды, модели и ностальгия по эпохе расцвета", "i": "📱", "c": "smartfony-i-planshety"}, {"s": "sozdanie-zagruzochnoj-fleshki-windows-xp-iz-iso-obraza", "t": "Создание загрузочной флешки Windows XP из ISO образа: пошаговая инструкция", "i": "🖥️", "c": "kompyutery-i-noutbuki"}, {"s": "sochetanie-klavish-chtoby-zakryt-programmu", "t": "Горячие клавиши для закрытия программы: Windows, Mac, Linux", "i": "🖥️", "c": "kompyutery-i-noutbuki"}, {"s": "soedinitel-dlya-shlanga-6mm", "t": "Соединитель для шланга 6 мм: выбор, виды и установка", "i": "📁", "c": "drugoe"}, {"s": "so-skolko-chasov-nachinaetsya-noch", "t": "Со скольки часов начинается ночь: астрономия, закон и режим сна", "i": "🏠", "c": "umnyj-dom"}, {"s": "sochetanie-bystrykh-klavish-na-klaviature", "t": "Сочетание быстрых клавиш на клавиатуре: полный гайд по хоткеям", "i": "🖥️", "c": "kompyutery-i-noutbuki"}, {"s": "sochetanie-klavish-chtoby-vybrat-vse", "t": "Сочетание клавиш чтобы выбрать все: полный гид для Windows, Mac и Linux", "i": "💿", "c": "soft-i-prilozheniya"}, {"s": "sony-ericsson-poslednyaya-model", "t": "Sony Ericsson: последняя модель и история бренда", "i": "📱", "c": "smartfony-i-planshety"}, {"s": "sozdanie-detskogo-apple-id", "t": "Создание детского Apple ID: полная инструкция для родителей", "i": "🔒", "c": "bezopasnost-i-akkaunty"}, {"s": "son-1206d-instruktsiya-na-russkom", "t": "SON 1206D Инструкция на русском: руководство, коды, ремонт", "i": "🚗", "c": "avtomobilnaya-elektronika"}, {"s": "sozdanie-rezby-v-kompas-3d", "t": "Создание резьбы в Компас-3D: пошаговая инструкция для 2D и 3D", "i": "🖨️", "c": "3d-pechat-i-modelirovanie"}, {"s": "sobaka-baskervilej-film-1971-smotret-onlajn-besplatno-v-khoroshem-kachestve", "t": "Собака Баскервилей (1971): как найти и посмотреть фильм онлайн", "i": "🎧", "c": "audio-i-video"}, {"s": "sochetanie-klavish-dlya-zameny-teksta", "t": "Сочетание клавиш для замены текста: полное руководство", "i": "💿", "c": "soft-i-prilozheniya"}, {"s": "sochetanie-klavish-s-kontrl", "t": "Комбинации клавиш с Ctrl: полный гид по горячим клавишам Windows", "i": "🖥️", "c": "kompyutery-i-noutbuki"}, {"s": "soobshchenie-5151-chto-eto", "t": "Ошибка 5151: что это значит и как исправить на смартфоне и ТВ", "i": "📱", "c": "smartfony-i-planshety"}, {"s": "sozdat-epl-ajdi-bez-nomera-telefona", "t": "Как создать Apple ID без номера телефона: 2026 Инструкция", "i": "📱", "c": "smartfony-i-planshety"}, {"s": "sozdat-paru-s-apple-watch-vruchnuyu", "t": "Как создать пару с Apple Watch вручную: полная инструкция", "i": "⌚", "c": "elektronika-i-gadzhety"}, {"s": "so-skolko-chasov-nachinaetsya-utro", "t": "Со скольки часов начинается утро: биологическое и астрономическое время", "i": "📁", "c": "drugoe"}, {"s": "sonoff-kak-podklyuchit-wifi", "t": "Как подключить Sonoff к Wi-Fi: полная инструкция 2026", "i": "🏠", "c": "umnyj-dom"}, {"s": "sound-blasterx-ae-5-plus", "t": "Sound BlasterX AE-5 Plus: Обзор, настройки и сравнение", "i": "🎧", "c": "audio-i-video"}, {"s": "sobrat-pk-s-nulya", "t": "Как собрать ПК с нуля: Пошаговая инструкция 2026", "i": "🖥️", "c": "kompyutery-i-noutbuki"}, {"s": "sochetanie-klavish-ctrl-f", "t": "Сочетание клавиш Ctrl F: как искать текст в браузере и Word", "i": "🖥️", "c": "kompyutery-i-noutbuki"}, {"s": "sochetanie-klavish-dlya-sokhraneniya-fajla", "t": "Горячие клавиши для сохранения файла: все комбинации и секреты", "i": "💿", "c": "soft-i-prilozheniya"}, {"s": "sokolov-podveska-bukva-a", "t": "Подвеска Соколов с буквой А: обзор, выбор и уход за украшением", "i": "📁", "c": "drugoe"}, {"s": "sotovyj-telefon-s-usilitelem-signala", "t": "Сотовый телефон с усилителем сигнала: как выбрать и установить репитер", "i": "📱", "c": "smartfony-i-planshety"}, {"s": "sovmestimost-aqara-i-xiaomi", "t": "Совместимость Aqara и Xiaomi: как подключить и настроить устройства", "i": "🏠", "c": "umnyj-dom"}, {"s": "sozdanie-modeli-dlya-chpu-frezera", "t": "Создание модели для ЧПУ фрезера: от CAD до G-кода", "i": "🖨️", "c": "3d-pechat-i-modelirovanie"}, {"s": "sochetanie-klavish-ctrl-d", "t": "Комбинация клавиш Ctrl+D: полное руководство по использованию в браузере и графических редакторах", "i": "🖥️", "c": "kompyutery-i-noutbuki"}, {"s": "sovmestimost-operativnoj-pamyati-dlya-noutbuka", "t": "Совместимость оперативной памяти для ноутбука: Полное руководство по апгрейду", "i": "🖥️", "c": "kompyutery-i-noutbuki"}, {"s": "sochetanie-klavish-sozdat-yarlyk", "t": "Сочетание клавиш создать ярлык на Windows: 5 способов", "i": "🖥️", "c": "kompyutery-i-noutbuki"}, {"s": "sochetaniya-klavish-dlya-pereimenovaniya-fajla", "t": "Сочетания клавиш для переименования файла: Windows, Mac и Linux", "i": "🖥️", "c": "kompyutery-i-noutbuki"}, {"s": "sozdanie-zagruzochnoj-fleshki-mak-os", "t": "Создание загрузочной флешки macOS: полная инструкция", "i": "🖥️", "c": "kompyutery-i-noutbuki"}, {"s": "so-skolki-schitaetsya-utro-den-vecher-i-noch", "t": "Со скольки считается утро, день, вечер и ночь: точное время", "i": "📁", "c": "drugoe"}, {"s": "soni-erikson-telefon-kupit", "t": "Купить телефон Sony Ericsson: выбор, цены и советы по поиску", "i": "📱", "c": "smartfony-i-planshety"}, {"s": "sotovye-vyshki-ryadom-so-mnoj-na-karte", "t": "Как найти сотовые вышки рядом со мной на карте: карты и приложения", "i": "📶", "c": "set-i-internet"}, {"s": "sotovyj-telefon-motorola-90-godov", "t": "Моторола 90-х: Легендарные модели, технологии и история эры GSM", "i": "📱", "c": "smartfony-i-planshety"}, {"s": "sozdanie-zagruzochnoj-fleshki-mac-os-catalina", "t": "Как создать загрузочную флешку macOS Catalina: Пошаговая инструкция", "i": "🖥️", "c": "kompyutery-i-noutbuki"}]