[{"s": "tl-wn727n-kak-podklyuchit-k-kompyuteru", "t": "TP-Link TL-WN727N: как подключить к компьютеру (Инструкция)", "i": "📶", "c": "set-i-internet"}, {"s": "tl-wr845n-v4-proshivka", "t": "TP-Link TL-WR845N V4: прошивка, сброс и настройка", "i": "📶", "c": "set-i-internet"}, {"s": "tl-wr850n-v2-proshivka", "t": "Прошивка TP-Link TL-WR850N v2: Инструкция, риски и альтернативы", "i": "📶", "c": "set-i-internet"}, {"s": "tl-wr841n-obnovlenie-po", "t": "TP-Link TL-WR841N: Обновление прошивки по шагам", "i": "📶", "c": "set-i-internet"}, {"s": "tl-wr840n-v6-proshivka", "t": "Прошивка TP-Link TL-WR840N v6: Инструкция, риски и сборка OpenWrt", "i": "📶", "c": "set-i-internet"}, {"s": "tl494-skhema-vklyucheniya-blok-pitaniya", "t": "TL494 схема включения блок питания: расчёт и настройка", "i": "🔧", "c": "remont-i-diagnostika"}, {"s": "tl-wr841n-v14-proshivka", "t": "Прошивка TP-Link TL-WR841N v14: инструкция, выбор версии и настройка", "i": "📶", "c": "set-i-internet"}, {"s": "tl-wr841n-v14-00000014-proshivka", "t": "Прошивка TP-Link TL-WR841N v14: версия 00000014, инструкция и риски", "i": "📶", "c": "set-i-internet"}, {"s": "tl-wr841n-v13-00000013-proshivka", "t": "TP-Link TL-WR841N V13 00000013: прошивка и восстановление", "i": "📶", "c": "set-i-internet"}, {"s": "tl-wr842n-v5-proshivka", "t": "TP-Link TL-WR842N V5: прошивка, сброс и настройка роутера", "i": "📶", "c": "set-i-internet"}]