[{"s": "uroven-ustanovit-na-telefon-stroitelnyj-besplatno", "t": "Как установить строительный уровень на телефон бесплатно: лучшие приложения", "i": "📱", "c": "smartfony-i-planshety"}, {"s": "uroven-signala-sotovoj-svyazi-v-detsibelakh-kakoj-luchshe", "t": "Уровень сигнала сотовой связи в дБм: какой показатель нормальный?", "i": "📱", "c": "smartfony-i-planshety"}, {"s": "uroven-na-telefone-stroitelnyj-onlajn-bez-skachivaniya-besplatno-na-russkom-bez-registratsii", "t": "Строительный уровень на телефоне онлайн бесплатно без скачивания", "i": "📱", "c": "smartfony-i-planshety"}, {"s": "uroven-na-telefone-vklyuchit", "t": "Как включить уровень на телефоне: скрытые функции, приложения и настройки", "i": "📱", "c": "smartfony-i-planshety"}, {"s": "uroki-pechati-na-3d-printere", "t": "Уроки печати на 3D принтере: от настройки до финишной обработки", "i": "🖨️", "c": "3d-pechat-i-modelirovanie"}, {"s": "urovni-gromkosti-v-db", "t": "Уровни громкости в дБ: таблица, нормы и безопасность", "i": "🎧", "c": "audio-i-video"}, {"s": "urok-po-sketchapu-dlya-nachinayushchikh", "t": "Урок по SketchUp для начинающих: Полное руководство с нуля", "i": "💿", "c": "soft-i-prilozheniya"}, {"s": "url-plejlista-dlya-iptv-m3u", "t": "Как найти и использовать URL плейлиста для IPTV M3U в 2026", "i": "📺", "c": "televizory-i-tv-pristavki"}, {"s": "uroven-platina-lukojl-chto-daet", "t": "Программа «Платина» от Лукойл: что дает, преимущества и условия участия", "i": "🚗", "c": "avtomobilnaya-elektronika"}, {"s": "uroven-stroitelnyj-v-telefone-onlajn", "t": "Уровень строительный в телефоне онлайн: как использовать датчики и приложения", "i": "📱", "c": "smartfony-i-planshety"}, {"s": "uroven-onlajn-stroitelnyj-bez-skachivaniya-na-telefone-besplatno", "t": "Онлайн-строитель: уровень без скачивания, бесплатно на телефоне", "i": "🎮", "c": "igry-i-razvlecheniya"}, {"s": "uroki-sketchap-dlya-nachinayushchikh", "t": "Уроки SketchUp для начинающих: полное руководство с нуля", "i": "🖨️", "c": "3d-pechat-i-modelirovanie"}, {"s": "uroki-avtomekhanika-dlya-nachinayushchikh", "t": "Уроки автомеханика для начинающих: с чего начать и как учиться", "i": "🚗", "c": "avtomobilnaya-elektronika"}, {"s": "uroven-shuma-v-detsibelakh-sravnenie-tablitsa", "t": "Уровень шума в децибелах: сравнение таблица и нормы", "i": "⌚", "c": "elektronika-i-gadzhety"}, {"s": "uroven-shuma-v-detsibelakh-norma", "t": "Уровень шума в децибелах: нормы и стандарты по СанПиН", "i": "🏠", "c": "umnyj-dom"}, {"s": "uroki-po-remontu-telefonov", "t": "Уроки по ремонту телефонов: с чего начать новичку", "i": "🔧", "c": "remont-i-diagnostika"}, {"s": "uroki-po-sketchapu-na-russkom-dlya-nachinayushchikh", "t": "Уроки по SketchUp на русском для начинающих: Полное руководство", "i": "🖨️", "c": "3d-pechat-i-modelirovanie"}, {"s": "uroven-shuma-v-detsibelakh-norma-dlya-cheloveka", "t": "Норма шума в дБ для человека: таблица уровней и допустимые значения", "i": "⌚", "c": "elektronika-i-gadzhety"}, {"s": "url-adres-plejlista-dlya-iptv", "t": "URL адрес плейлиста для IPTV: как найти и настроить ссылку", "i": "📺", "c": "televizory-i-tv-pristavki"}, {"s": "url-dlya-iptv-besplatno", "t": "URL для IPTV бесплатно: топ плееров, плейлистов и настройка в 2026", "i": "📺", "c": "televizory-i-tv-pristavki"}, {"s": "uroki-sketchap-dlya-nachinayushchikh-besplatno", "t": "Уроки SketchUp для начинающих: полное бесплатное руководство", "i": "🖨️", "c": "3d-pechat-i-modelirovanie"}, {"s": "uroki-po-home-assistant", "t": "Уроки по Home Assistant: Гид по умному дому с нуля", "i": "🏠", "c": "umnyj-dom"}, {"s": "uroven-dlya-telefona-android", "t": "Уровень в телефоне на Android: как включить, настроить и использовать", "i": "📱", "c": "smartfony-i-planshety"}, {"s": "uroven-signala-sotovoj-svyazi-v-detsibelakh", "t": "Уровень сигнала сотовой связи в децибелах: как измерить и улучшить", "i": "📶", "c": "set-i-internet"}, {"s": "uroki-sketchap-na-russkom-yazyke", "t": "Уроки SketchUp на русском: полное руководство для новичков", "i": "🖨️", "c": "3d-pechat-i-modelirovanie"}, {"s": "uroven-shuma-i-uroven-zvukovogo-davleniya-v-chem-raznitsa", "t": "Уровень шума и звукового давления: в чем разница для акустики", "i": "🎧", "c": "audio-i-video"}, {"s": "uroven-na-telefone-stroitelnyj-skachat-na-android", "t": "Уровень на телефон строительный: скачать для Android, лучшие приложения", "i": "💿", "c": "soft-i-prilozheniya"}, {"s": "uroven-zvuka-v-db", "t": "Уровень звука в дБ: таблица, нормы и влияние на слух", "i": "🎧", "c": "audio-i-video"}, {"s": "urovni-shuma-v-detsibelakh-tablitsa", "t": "Уровни шума в децибелах: полная таблица (дБА)", "i": "⌚", "c": "elektronika-i-gadzhety"}, {"s": "urovni-shuma-v-db-chemu-sootvetstvuyut", "t": "Уровень шума в дБ: таблица соответствий и нормы для дома", "i": "🎧", "c": "audio-i-video"}, {"s": "uroven-stroitelnyj-v-telefone-onlajn-besplatno", "t": "Уровень строительный в телефоне онлайн: бесплатный инструмент за 1 минуту", "i": "📱", "c": "smartfony-i-planshety"}, {"s": "uroven-zvuka-postoyannogo-shuma", "t": "Норма уровня звука постоянного шума: измерения и защита слуха", "i": "🎧", "c": "audio-i-video"}, {"s": "url-zablokirovannogo-kanala-youtube", "t": "Что делать, если URL заблокированного канала YouTube не работает?", "i": "🎧", "c": "audio-i-video"}]