[{"s": "zona-na-samsung-smart-tv", "t": "Зона на Samsung Smart TV: Настройка, Очистка и Управление регионами", "i": "📺", "c": "televizory-i-tv-pristavki"}, {"s": "zont-ne-na-svyazi-chto-delat", "t": "Zont не на связи: причины сбоя и способы восстановления", "i": "🏠", "c": "umnyj-dom"}, {"s": "zona-dlya-tv-lg", "t": "Зона для ТВ LG: поиск, настройка и ремонт проблемных участков", "i": "📺", "c": "televizory-i-tv-pristavki"}, {"s": "zona-kak-smotret-na-televizore", "t": "Как смотреть Zona на телевизоре: Полная инструкция 2026", "i": "📺", "c": "televizory-i-tv-pristavki"}, {"s": "zont-net-svyazi-s-ustrojstvom", "t": "Zont нет связи с устройством: причины, диагностика и пошаговое решение", "i": "🚗", "c": "avtomobilnaya-elektronika"}, {"s": "zona-dlya-tizen-samsung-skachat", "t": "Zona для Samsung Tizen: установка и альтернативы 2026", "i": "📺", "c": "televizory-i-tv-pristavki"}, {"s": "zona-dlya-media-station-x", "t": "Zona для Media Station X: Установка и настройка 2026", "i": "📺", "c": "televizory-i-tv-pristavki"}, {"s": "zont-pogoda-iz-interneta", "t": "Zont погода из интернета: сброс и настройка датчиков", "i": "🏠", "c": "umnyj-dom"}, {"s": "zombi-protiv-rastenij-lego-multik", "t": "Лего Зомби против Растений: Обзор мультиков, фигурок и идей для сборки", "i": "🎮", "c": "igry-i-razvlecheniya"}, {"s": "zona-na-android-ne-rabotaet", "t": "Почему не работает Зона на Андроид: причины и способы fix", "i": "📱", "c": "smartfony-i-planshety"}, {"s": "zona-skachat-dlya-tizen", "t": "Как скачать и установить приложение Zona на телевизор Samsung Tizen", "i": "📺", "c": "televizory-i-tv-pristavki"}, {"s": "zona-filmy-dlya-smart-tv", "t": "Зона Кино на Смарт ТВ: как установить, настроить и смотреть фильмы", "i": "📺", "c": "televizory-i-tv-pristavki"}, {"s": "zolotoe-sechenie-eto-litsa", "t": "Золотое сечение лица: как найти идеальные пропорции и черты", "i": "📁", "c": "drugoe"}, {"s": "zona-hd-dlya-android-tv", "t": "Zona HD для Android TV: установка и настройка на телевизоре", "i": "📺", "c": "televizory-i-tv-pristavki"}, {"s": "zolotoe-sechenie-v-kosmetologii", "t": "Золотое сечение в косметологии: секрет идеальных пропорций", "i": "📁", "c": "drugoe"}, {"s": "zona-dlya-tizen-os", "t": "Zona для Tizen OS: установка на Samsung TV или альтернативы", "i": "📺", "c": "televizory-i-tv-pristavki"}, {"s": "zont-online-ru-lichnyj", "t": "Личный кабинет Zont Online: Вход, настройки и управление авто", "i": "🚗", "c": "avtomobilnaya-elektronika"}, {"s": "zona-ne-ustanavlivaetsya-na-android-tv", "t": "Zona не устанавливается на Android TV: причины и решение", "i": "📺", "c": "televizory-i-tv-pristavki"}, {"s": "zona-ustanovit-na-televizor-lg", "t": "Как установить Zona на телевизор LG: пошаговая инструкция", "i": "📺", "c": "televizory-i-tv-pristavki"}, {"s": "zolotoj-dvorets-serial-1992-1993", "t": "Сериал Золотой дворец (1992-1993): история, актеры и факты", "i": "🎮", "c": "igry-i-razvlecheniya"}, {"s": "zona-dlya-android-tv-4pda", "t": "Zona для Android TV 4PDA: установка и настройка приложения", "i": "📺", "c": "televizory-i-tv-pristavki"}, {"s": "zolotoj-uroven-lukojl-chto-daet", "t": "Золотой уровень Лукойл: бонусы, скидки и привилегии программы", "i": "📁", "c": "drugoe"}, {"s": "zona-dlya-webos-lg-smart-tv", "t": "Zona на LG Smart TV: установка, настройка и альтернативы", "i": "📺", "c": "televizory-i-tv-pristavki"}, {"s": "zont-onlajn-ru-podklyuchenie-k-kotlam", "t": "Зонт онлайн ру: подключение к котлам и настройка АСКУЭ", "i": "🏠", "c": "umnyj-dom"}, {"s": "zolotoe-sechenie-po-litsu", "t": "Золотое сечение по лицу: расчет идеальных пропорций и анализ", "i": "⌚", "c": "elektronika-i-gadzhety"}, {"s": "zona-skachat-apk-dlya-android-tv", "t": "Зона скачать APK для Android TV: безопасные источники и инструкции", "i": "📺", "c": "televizory-i-tv-pristavki"}, {"s": "zolotoe-sechenie-muzhskogo-litsa", "t": "Золотое сечение мужского лица: параметры, маски и эстетика", "i": "📁", "c": "drugoe"}, {"s": "zona-ustanovit-na-televizor-samsung", "t": "Как установить Zona на телевизор Samsung: пошаговая инструкция", "i": "📺", "c": "televizory-i-tv-pristavki"}, {"s": "zona-dlya-smart-tv-skachat", "t": "Zona для Smart TV: как скачать и установить на Android", "i": "📺", "c": "televizory-i-tv-pristavki"}, {"s": "zona-na-tizen-smart-tv", "t": "Zona на Tizen Smart TV: инструкция по установке и настройке", "i": "📺", "c": "televizory-i-tv-pristavki"}, {"s": "zona-na-televizor-android", "t": "Zona на телевизор Android: установка и настройка 2026", "i": "📺", "c": "televizory-i-tv-pristavki"}, {"s": "zona-dlya-televizora-na-android", "t": "Zona на телевизор Android: установка, настройка и решение проблем", "i": "📺", "c": "televizory-i-tv-pristavki"}, {"s": "zolotye-azs-lukojl-na-karte", "t": "Золотые АЗС Лукойл на карте: поиск, статус и привилегии", "i": "🚗", "c": "avtomobilnaya-elektronika"}, {"s": "zona-pokrytiya-turaya-sputnikovaya-svyaz", "t": "Зона покрытия Турайя: карта спутниковой связи и роуминг", "i": "📶", "c": "set-i-internet"}, {"s": "zona-ne-udalos-poluchit-informatsiyu-o-videofajle", "t": "Ошибка ZONA: не удалось получить информацию о видеофайле", "i": "💿", "c": "soft-i-prilozheniya"}, {"s": "zona-dlya-samsung-tv", "t": "Zona для Samsung TV: установка, настройка и устранение проблем", "i": "📺", "c": "televizory-i-tv-pristavki"}, {"s": "zona-ne-gruzit-filmy-na-televizore", "t": "Зона не грузит фильмы на телевизоре: причины и решения", "i": "📺", "c": "televizory-i-tv-pristavki"}, {"s": "zolotoe-sechenie-litsa-zhenshchiny-kak-rasschitat-onlajn-besplatno", "t": "Золотое сечение лица: онлайн расчет бесплатно и анализ", "i": "📁", "c": "drugoe"}, {"s": "zolotoe-sechenie-v-litse-cheloveka", "t": "Золотое сечение в лице: формула идеальной красоты и пропорций", "i": "📁", "c": "drugoe"}, {"s": "zona-apk-fajl-na-televizor", "t": "Зона APK файл на телевизор: Как установить приложения на Smart TV", "i": "📺", "c": "televizory-i-tv-pristavki"}, {"s": "zona-dlya-android-pristavki", "t": "Приложение ZONA для Android TV: установка, настройка и решение проблем", "i": "📺", "c": "televizory-i-tv-pristavki"}, {"s": "zona-ne-rabotaet-na-android-tv", "t": "Zona не работает на Android TV: причины, исправление ошибок и настройка", "i": "📺", "c": "televizory-i-tv-pristavki"}, {"s": "zont-ne-podklyuchaetsya-k-wifi", "t": "Zont не подключается к WiFi: причины, исправление, настройка", "i": "🚗", "c": "avtomobilnaya-elektronika"}, {"s": "zont-smart-new-skhema-podklyucheniya", "t": "Zont Smart New: схема подключения и настройка", "i": "🏠", "c": "umnyj-dom"}, {"s": "zona-ne-rabotaet-sejchas", "t": "Zona не работает сейчас: причины, диагностика и способы решения", "i": "💿", "c": "soft-i-prilozheniya"}, {"s": "zont-podklyuchenie-k-wifi", "t": "Zont подключение к WiFi: пошаговая инструкция и настройка", "i": "🏠", "c": "umnyj-dom"}, {"s": "zont-net-svyazi-s-serverom", "t": "Ошибки связи Zont: причины и способы устранения", "i": "🚗", "c": "avtomobilnaya-elektronika"}, {"s": "zona-android-tv-skachat-besplatno", "t": "Зона Андроид ТВ: Скачать бесплатно безопасные версии и APK", "i": "📺", "c": "televizory-i-tv-pristavki"}, {"s": "zona-skachat-na-televizor-xiaomi", "t": "Как скачать и установить приложение Zona на телевизор Xiaomi (Android TV)", "i": "📺", "c": "televizory-i-tv-pristavki"}, {"s": "zona-dlya-tizen-samsung", "t": "Zona для Tizen Samsung: Установка, настройка и решение проблем", "i": "📺", "c": "televizory-i-tv-pristavki"}, {"s": "zond-s-kameroj-dlya-smartfona", "t": "Зонд с камерой для смартфона: выбор, подключение и использование", "i": "🔧", "c": "remont-i-diagnostika"}]